<?xml version="1.0" encoding="UTF-8"?><PageFlow created="10.12.2019 15:01:10" createdBy="Lyonel" descriptor="PH_DATEI_021" filename="Kurzantrag_PNr_#ANTRAG_PROJEKTNUMMER#" guid="a77fe33f-6d42-4510-a640-1d72dbc84607" headline="" label="" modified="15.09.2025 09:31:03" modifiedBy="Lyonel" name="Kurzantrag_Historie" print="LaF_Kurzantrag_hoch" printFirst="" source="ecg-e2020-vor" timestamp="24.02.2026 11:10:28" uuid="8a6ed431-2ed3-4c34-bed4-acaec41fda70" version="v5.17.2995 (bc072f56)">
  <Webpage avoidPagebreak="false" created="10.12.2019 15:01:10" createdBy="Lyonel" guid="4058bfe0-1bc5-4bae-a239-88d4adf84ebd" heading="Projektzuordnung" hideIfEmpty="false" modified="15.09.2025 09:31:03" modifiedBy="Lyonel" print="" sortIndex="0" uuid="37b9daa0-fd39-4fc4-9eb2-28d0384c7582">
    <FormDefinition collapsed="false" created="10.12.2019 15:01:10" createdBy="Lyonel" forPDF="true" forWeb="true" guid="199621d5-b34a-44a3-aabb-7f7da1c58974" heading="1.1 Projektangaben" modified="15.09.2025 09:31:03" modifiedBy="Lyonel" sortIndex="0" uuid="39ffc131-658d-4579-bc95-9d94b769d6cd" visibility="">
      <FormComponent created="15.09.2025 09:31:03" descriptor="FIXEDTEXT_001" importKey="FIXEDTEXT_001" info="" label="" mandatory="false" modified="15.09.2025 09:31:03" param1="" param10="" param11="" param12="" param13="" param14="" param15="" param16="" param17="" param18="" param19="" param2="" param20="" param3="" param4="" param5="" param6="" param7="" param8="" param9="" readonly="false" richCLOB="" showErrors="true" sortIndex="0" sourceType="" submitOnChange="false" type="FIXEDRICHTEXT" usageType="" useLabelLeft="false" uuid="f7eb4ce8-a5a3-4d84-b8d6-6c728a48a5e8"/>
      <FormComponent created="15.09.2025 09:31:03" descriptor="ANTRAG_NAME" importKey="ANTRAG_NAME" info="Gewährung einer Zuwendung für das eingereichte Konzept gemäß des durchgeführten Interessenbekundungsverfahrens" label="" mandatory="true" modified="15.09.2025 09:31:03" param1="100" param10="" param11="" param12="" param13="" param14="" param15="" param16="" param17="" param18="" param19="" param2="" param20="" param3="" param4="" param5="" param6="" param7="" param8="" param9="" readonly="false" richCLOB="" showErrors="true" sortIndex="1" sourceType="SELF" submitOnChange="false" type="TEXTFIELD" usageType="" useLabelLeft="true" uuid="3639fbe4-0bc1-41cd-bff1-44ddcedaa1f9"/>
      <FormComponent created="15.09.2025 09:31:03" descriptor="ANTRAG_AKTENZEICHEN" importKey="ANTRAG_AKTENZEICHEN" info="Optionales Eingabefeld für ein evtl. Aktenzeichen der BwS" label="Aktenzeichen" mandatory="false" modified="15.09.2025 09:31:03" param1="100" param10="" param11="" param12="" param13="" param14="" param15="" param16="" param17="" param18="" param19="" param2="" param20="" param3="" param4="" param5="" param6="" param7="" param8="" param9="" readonly="false" richCLOB="" showErrors="true" sortIndex="2" sourceType="SELF" submitOnChange="false" type="TEXTFIELD" usageType="" useLabelLeft="true" uuid="c44f2812-66c5-4558-9ea4-d3146c4fc00f"/>
      <FormComponent created="15.09.2025 09:31:03" descriptor="ANTRAG_LAUFZEIT_BEGINN" importKey="ANTRAG_LAUFZEIT_BEGINN" info="" label="Projektlaufzeit" mandatory="false" modified="15.09.2025 09:31:03" param1="" param10="" param11="" param12="" param13="" param14="" param15="" param16="" param17="" param18="" param19="" param2="" param20="" param3="" param4="" param5="" param6="" param7="" param8="" param9="" readonly="false" richCLOB="" showErrors="true" sortIndex="3" sourceType="SELF" submitOnChange="false" type="LAUFZEIT" usageType="" useLabelLeft="true" uuid="6bb66a28-fe16-40b2-9253-90d67d5be8ce"/>
      <FormComponent created="15.09.2025 09:31:03" descriptor="FIXEDTEXT_010" importKey="FIXEDTEXT_010" info="" label="" mandatory="false" modified="15.09.2025 09:31:03" param1="" param10="" param11="" param12="" param13="" param14="" param15="" param16="" param17="" param18="" param19="" param2="" param20="" param3="" param4="" param5="" param6="" param7="" param8="" param9="" readonly="false" richCLOB="&lt;p&gt;Die Projektlaufzeit sollte auch etwaige zu fördernde Vor- und Nachbereitungszeiten berücksichtigen.&lt;/p&gt;" showErrors="true" sortIndex="4" sourceType="" submitOnChange="false" type="FIXEDRICHTEXT" usageType="" useLabelLeft="false" uuid="6e668b25-8e2c-4689-bb5a-d2d10e0d1c37"/>
    </FormDefinition>
    <FormDefinition collapsed="false" created="10.12.2019 15:01:10" createdBy="Lyonel" forPDF="true" forWeb="true" guid="a0764a7f-52e1-4d17-82cc-1bc8d53746a4" heading="1.2 Projektzuordnung" modified="15.09.2025 09:31:03" modifiedBy="Lyonel" sortIndex="1" uuid="9d6db923-3b39-4785-94b1-33aefdea00f0" visibility="">
      <FormComponent created="15.09.2025 09:31:03" descriptor="ANTRAG_PROMOLEVEL" importKey="ANTRAG_PROMOLEVEL" info="" label="Förderinstrument" mandatory="true" modified="15.09.2025 09:31:03" param1="" param10="" param11="" param12="" param13="" param14="" param15="" param16="" param17="" param18="" param19="" param2="" param20="" param3="" param4="" param5="" param6="" param7="" param8="" param9="" readonly="false" richCLOB="" showErrors="false" sortIndex="0" sourceType="SELF" submitOnChange="false" type="PROMOLEVEL_INSTRUMENT_DISPLAY" usageType="" useLabelLeft="true" uuid="4ed677ca-21c8-4525-afa2-bdce65abd144"/>
    </FormDefinition>
    <FormDefinition collapsed="false" created="10.12.2019 15:01:10" createdBy="Lyonel" forPDF="true" forWeb="true" guid="847386bf-99f8-4d0d-8de5-a782a6f725b7" heading="" modified="15.09.2025 09:31:03" modifiedBy="Lyonel" sortIndex="2" uuid="3db3e348-83ac-4524-8b62-bd6fd5c789ae" visibility="">
      <FormComponent created="15.09.2025 09:31:03" descriptor="ANTRAG_FINANZIERUNGSART" importKey="ANTRAG_FINANZIERUNGSART" info="" label="" mandatory="true" modified="15.09.2025 09:31:03" param1="Fehlbedarfsfinanzierung" param10="" param11="" param12="" param13="" param14="" param15="" param16="" param17="" param18="" param19="" param2="" param20="" param3="" param4="" param5="" param6="ja" param7="" param8="" param9="" readonly="true" richCLOB="" showErrors="true" sortIndex="0" sourceType="SELF" submitOnChange="false" type="SELECT_ONE_MENU" usageType="" useLabelLeft="true" uuid="81ed7c23-15bf-468c-9898-b8213bc20724"/>
    </FormDefinition>
    <FormDefinition collapsed="false" created="10.12.2019 15:01:10" createdBy="Lyonel" forPDF="true" forWeb="true" guid="707f3259-a545-4d61-833f-ea6f7037baeb" heading="" modified="15.09.2025 09:31:03" modifiedBy="Lyonel" sortIndex="3" uuid="f73dcb95-3807-4de8-b91c-8d6a7fa72522" visibility="#GEGENSTAND.LEVEL_CODE# ~ 'BVBO'">
      <FormComponent created="15.09.2025 09:31:03" descriptor="ANTRAG_PROJEKTLEIS" importKey="ANTRAG_PROJEKTLEIS" info="" label="" mandatory="true" modified="15.09.2025 09:31:03" param1="" param10="" param11="" param12="" param13="" param14="" param15="" param16="" param17="" param18="" param19="" param2="" param20="" param3="" param4="" param5="" param6="ja" param7="" param8="" param9="" readonly="true" richCLOB="" showErrors="false" sortIndex="0" sourceType="SELF" submitOnChange="false" type="SELECT_ONE_MENU" usageType="" useLabelLeft="true" uuid="b5400742-acb3-4eb7-9b7c-abdcc3169cee"/>
      <FormComponent created="15.09.2025 09:31:03" descriptor="FIXEDTEXT_001" importKey="FIXEDTEXT_001" info="" label="" mandatory="false" modified="15.09.2025 09:31:03" param1="" param10="" param11="" param12="" param13="" param14="" param15="" param16="" param17="" param18="" param19="" param2="" param20="" param3="" param4="" param5="" param6="" param7="" param8="" param9="" readonly="false" richCLOB="&lt;p&gt;Hierbei handelt es sich um berufsorientierende Qualifizierung.&lt;/p&gt;" showErrors="true" sortIndex="1" sourceType="" submitOnChange="false" type="FIXEDRICHTEXT" usageType="" useLabelLeft="false" uuid="27e5cae6-84cd-431e-b454-eb3264408def"/>
    </FormDefinition>
    <FormDefinition collapsed="false" created="22.02.2025 15:14:51" createdBy="Lyonel" forPDF="true" forWeb="true" guid="c2e7a5d6-1469-4776-8f1f-945c6449b484" heading="" modified="15.09.2025 09:31:03" modifiedBy="Lyonel" sortIndex="4" uuid="209193fd-eb19-4b39-9eaf-972ef7920202" visibility="#GEGENSTAND.LEVEL_CODE# == 'KaT'">
      <FormComponent created="15.09.2025 09:31:03" descriptor="ANTRAG_PROJEKTLEIS" importKey="ANTRAG_PROJEKTLEIS" info="" label="" mandatory="true" modified="15.09.2025 09:31:03" param1="" param10="" param11="" param12="" param13="" param14="" param15="" param16="" param17="" param18="" param19="" param2="" param20="" param3="" param4="" param5="" param6="ja" param7="" param8="" param9="" readonly="true" richCLOB="" showErrors="false" sortIndex="0" sourceType="SELF" submitOnChange="false" type="SELECT_ONE_MENU" usageType="" useLabelLeft="true" uuid="fcae2f0d-2d23-41f6-84ca-b60d97be8111"/>
    </FormDefinition>
    <FormDefinition collapsed="false" created="10.12.2019 15:01:10" createdBy="Lyonel" forPDF="true" forWeb="true" guid="2786c4cc-6e10-43be-a4ae-edceed00a1c6" heading="" modified="15.09.2025 09:31:03" modifiedBy="Lyonel" sortIndex="5" uuid="05454c59-40c1-41d2-9371-0bcc6e275e1c" visibility="#GEGENSTAND.LEVEL_CODE# ~ 'BVBO'">
      <FormComponent created="15.09.2025 09:31:03" descriptor="BILDUNG_BERLIN_BEZIRK" importKey="BILDUNG_BERLIN_BEZIRK" info="" label="" mandatory="true" modified="15.09.2025 09:31:03" param1="" param10="" param11="" param12="" param13="" param14="" param15="" param16="" param17="" param18="" param19="" param2="" param20="" param3="" param4="" param5="" param6="ja" param7="" param8="" param9="" readonly="false" richCLOB="" showErrors="true" sortIndex="0" sourceType="SELF" submitOnChange="true" type="SELECT_ONE_MENU" usageType="" useLabelLeft="true" uuid="7b3003a8-8f02-463f-92e5-aed9cdae7586"/>
      <FormComponent created="15.09.2025 09:31:03" descriptor="BILDUNG_BERLIN_OBERSCHULE" importKey="BILDUNG_BERLIN_OBERSCHULE" info="" label="" mandatory="true" modified="15.09.2025 09:31:03" param1="" param10="" param11="" param12="" param13="" param14="" param15="" param16="" param17="" param18="" param19="" param2="" param20="" param3="" param4="" param5="" param6="ja" param7="" param8="" param9="" readonly="false" richCLOB="" showErrors="false" sortIndex="1" sourceType="SELF" submitOnChange="true" type="SELECT_ONE_MENU" usageType="" useLabelLeft="true" uuid="039fed83-f2b7-4c67-be0d-9c26c860b137"/>
      <FormComponent created="15.09.2025 09:31:03" descriptor="PH_NKL_053" importKey="PH_NKL_053" info="" label="" mandatory="true" modified="15.09.2025 09:31:03" param1="2020/2021" param10="" param11="" param12="" param13="" param14="" param15="" param16="" param17="" param18="" param19="" param2="" param20="" param3="" param4="" param5="" param6="ja" param7="" param8="" param9="" readonly="false" richCLOB="" showErrors="true" sortIndex="2" sourceType="SELF" submitOnChange="false" type="SELECT_ONE_MENU" usageType="" useLabelLeft="true" uuid="c820dab4-84cd-47f4-88bb-c4ca663c507d"/>
    </FormDefinition>
    <FormDefinition collapsed="false" created="14.06.2022 16:58:12" createdBy="Lyonel" forPDF="true" forWeb="true" guid="990f934a-6fce-4aee-927e-dbb37934dafb" heading="" modified="15.09.2025 09:31:03" modifiedBy="Lyonel" sortIndex="6" uuid="f7ba2e58-50c9-4016-b38b-1bc0c18223de" visibility="#GEGENSTAND.LEVEL_CODE# ~ 'BVBO'">
      <FormComponent created="15.09.2025 09:31:03" descriptor="BILDUNG_JAHRGANGSSTUFE" importKey="BILDUNG_JAHRGANGSSTUFE" info="" label="" mandatory="true" modified="15.09.2025 09:31:03" param1="" param10="" param11="" param12="" param13="" param14="" param15="" param16="" param17="" param18="" param19="" param2="" param20="" param3="" param4="" param5="" param6="" param7="" param8="" param9="" readonly="false" richCLOB="" showErrors="false" sortIndex="0" sourceType="SELF" submitOnChange="false" type="SELECT_MANY_CHECKBOX" usageType="" useLabelLeft="true" uuid="c481d071-7f96-4166-b591-13d37683cd34"/>
    </FormDefinition>
  </Webpage>
  <Webpage avoidPagebreak="false" created="10.12.2019 15:01:10" createdBy="Lyonel" guid="139785ca-ae9c-4632-b649-c8f3e4ebd185" heading="BwS-Zuwendungsempfänger" hideIfEmpty="false" modified="15.09.2025 09:31:03" modifiedBy="Lyonel" print="" sortIndex="1" uuid="339c4af5-4342-4018-af81-914686274bb8">
    <FormDefinition collapsed="false" created="10.12.2019 15:01:10" createdBy="Lyonel" forPDF="true" forWeb="true" guid="455e8095-2237-4219-9d4d-4e3e898a40eb" heading="1.3 Bewilligende Stelle" modified="15.09.2025 09:31:03" modifiedBy="Lyonel" sortIndex="0" uuid="a183caaf-d84d-4b27-b958-8f31401f0b06" visibility="">
      <FormComponent created="15.09.2025 09:31:03" descriptor="KONTAKT_PERSON_ZGS" importKey="KONTAKT_PERSON_ZGS" info="" label=" " mandatory="true" modified="15.09.2025 09:31:03" param1="" param10="Bewilligende Stelle" param11="" param12="" param13="" param14="" param15="" param16="" param17="" param18="" param19="" param2="" param20="" param3="" param4="Ja" param5="" param6="" param7="" param8="" param9="Ja" readonly="false" richCLOB="" showErrors="true" sortIndex="0" sourceType="SELF" submitOnChange="false" type="KONTAKTPERSON" usageType="" useLabelLeft="false" uuid="d8415e48-e3b1-48c3-a566-21dddb6fed1f"/>
    </FormDefinition>
    <FormDefinition collapsed="false" created="10.12.2019 15:01:10" createdBy="Lyonel" forPDF="true" forWeb="true" guid="8f762ea3-423d-400a-8718-0e6bc118b2a8" heading="" modified="15.09.2025 09:31:03" modifiedBy="Lyonel" sortIndex="1" uuid="c09ad3e3-5711-4b9a-801e-1289629a2432" visibility="">
      <FormComponent created="15.09.2025 09:31:03" descriptor="KONTAKT_PERSON_SB2" importKey="KONTAKT_PERSON_SB2" info="" label="Zweite Kontaktperson" mandatory="false" modified="15.09.2025 09:31:03" param1="" param10="" param11="" param12="" param13="" param14="" param15="" param16="" param17="" param18="" param19="" param2="ja" param20="" param3="ja" param4="ja" param5="ja" param6="ja" param7="ja" param8="ja" param9="" readonly="false" richCLOB="" showErrors="true" sortIndex="0" sourceType="SELF" submitOnChange="false" type="KONTAKTPERSON" usageType="" useLabelLeft="false" uuid="e5cb130f-8f25-4167-9077-121a6cdbd82a"/>
    </FormDefinition>
    <FormDefinition collapsed="false" created="11.07.2024 12:24:42" createdBy="Lyonel" forPDF="true" forWeb="true" guid="28dac064-fa4e-41a5-8866-f913dd332570" heading="" modified="15.09.2025 09:31:03" modifiedBy="Lyonel" sortIndex="2" uuid="ef7398a3-29bd-45ce-bfcd-0df2b670604e" visibility="BO_STATUS ~ 'KA10'">
      <FormComponent created="15.09.2025 09:31:03" descriptor="KONTAKT_PERSON_RES" importKey="KONTAKT_PERSON_RES" info="" label="Bewilligung durch" mandatory="false" modified="15.09.2025 09:31:03" param1="" param10="" param11="" param12="" param13="" param14="" param15="" param16="" param17="" param18="" param19="" param2="ja" param20="" param3="ja" param4="ja" param5="ja" param6="ja" param7="ja" param8="ja" param9="ja" readonly="false" richCLOB="" showErrors="false" sortIndex="0" sourceType="SELF" submitOnChange="false" type="KONTAKTPERSON" usageType="" useLabelLeft="false" uuid="10d28a40-ebb5-45f5-9c21-e5fa6443068d"/>
    </FormDefinition>
    <FormDefinition collapsed="false" created="10.12.2019 15:01:10" createdBy="Lyonel" forPDF="true" forWeb="true" guid="9462f8c0-bf5b-4ca8-abc1-78254093dc24" heading="" modified="15.09.2025 09:31:03" modifiedBy="Lyonel" sortIndex="3" uuid="75c44c02-6f9b-466d-a5ff-41f020fbed02" visibility="BO_STATUS !~ 'KA10'">
      <FormComponent created="15.09.2025 09:31:03" descriptor="KONTAKT_PERSON_RES" importKey="KONTAKT_PERSON_RES" info="" label="Bewilligung durch" mandatory="true" modified="15.09.2025 09:31:03" param1="" param10="" param11="" param12="" param13="" param14="" param15="" param16="" param17="" param18="" param19="" param2="Ja" param20="" param3="Ja" param4="Ja" param5="Ja" param6="Ja" param7="Ja" param8="Ja" param9="Ja" readonly="false" richCLOB="" showErrors="false" sortIndex="0" sourceType="SELF" submitOnChange="false" type="KONTAKTPERSON" usageType="" useLabelLeft="false" uuid="96dbbc42-199c-4736-8a73-d69637c3f791"/>
    </FormDefinition>
    <FormDefinition collapsed="false" created="10.12.2019 15:01:10" createdBy="Lyonel" forPDF="true" forWeb="true" guid="38da327d-798f-4e57-a811-ebfaacd4b12e" heading="1.4 Zuwendungsempfänger" modified="15.09.2025 09:31:03" modifiedBy="Lyonel" sortIndex="4" uuid="d02c0150-6e06-43c8-a465-aca616c1625a" visibility="">
      <FormComponent created="15.09.2025 09:31:03" descriptor="KONTAKT_PERSON_AST" importKey="KONTAKT_PERSON_AST" info="" label=" " mandatory="true" modified="15.09.2025 09:31:03" param1="" param10="" param11="" param12="" param13="" param14="" param15="" param16="" param17="" param18="" param19="" param2="" param20="" param3="" param4="" param5="" param6="" param7="" param8="" param9="" readonly="false" richCLOB="" showErrors="true" sortIndex="0" sourceType="SELF" submitOnChange="false" type="KONTAKTPERSON" usageType="" useLabelLeft="false" uuid="5d585583-da90-4429-ad06-2143c9f58133"/>
      <FormComponent created="15.09.2025 09:31:03" descriptor="FIXEDTEXT_002" importKey="FIXEDTEXT_002" info="" label="" mandatory="false" modified="15.09.2025 09:31:03" param1="" param10="" param11="" param12="" param13="" param14="" param15="" param16="" param17="" param18="" param19="" param2="" param20="" param3="" param4="" param5="" param6="" param7="" param8="" param9="" readonly="false" richCLOB="&lt;p&gt;&amp;nbsp;&lt;/p&gt;&#13;&#10;&lt;p&gt;&lt;strong&gt;&lt;span style=&quot;font-size: small;&quot;&gt;Zur rechtsgeschäftlichen Vertretung befugte Personen&lt;/span&gt;&lt;/strong&gt;&lt;/p&gt;&#13;&#10;&lt;p&gt;&lt;strong&gt;&lt;span style=&quot;font-size: small;&quot;&gt;&lt;br&gt;&lt;/span&gt;&lt;/strong&gt;&lt;/p&gt;" showErrors="true" sortIndex="1" sourceType="" submitOnChange="false" type="FIXEDRICHTEXT" usageType="" useLabelLeft="false" uuid="5873ae4f-f83b-4c61-91d9-edeb5a82cbe3"/>
      <FormComponent created="15.09.2025 09:31:03" descriptor="ANTRAG_VERTRETUNG_ANREDE" importKey="ANTRAG_VERTRETUNG_ANREDE" info="" label="" mandatory="true" modified="15.09.2025 09:31:03" param1="" param10="" param11="" param12="" param13="" param14="" param15="" param16="" param17="" param18="" param19="" param2="" param20="" param3="" param4="" param5="" param6="" param7="" param8="" param9="" readonly="false" richCLOB="" showErrors="true" sortIndex="2" sourceType="SELF" submitOnChange="false" type="SELECT_ONE_RADIO_TABLE" usageType="" useLabelLeft="true" uuid="1e6e44ad-acd8-4d97-bf9e-c292b63372a2"/>
      <FormComponent created="15.09.2025 09:31:03" descriptor="ANTRAG_VERTRETUNG_TITEL" importKey="ANTRAG_VERTRETUNG_TITEL" info="" label="" mandatory="false" modified="15.09.2025 09:31:03" param1="" param10="" param11="" param12="" param13="" param14="" param15="" param16="" param17="" param18="" param19="" param2="" param20="" param3="" param4="" param5="" param6="" param7="" param8="" param9="" readonly="false" richCLOB="" showErrors="true" sortIndex="3" sourceType="SELF" submitOnChange="false" type="TEXTFIELD" usageType="" useLabelLeft="true" uuid="8ec16a23-8dec-4901-b3ea-da3585bef016"/>
      <FormComponent created="15.09.2025 09:31:03" descriptor="ANTRAG_VERTRETUNG_VORNAME" importKey="ANTRAG_VERTRETUNG_VORNAME" info="" label="" mandatory="true" modified="15.09.2025 09:31:03" param1="" param10="" param11="" param12="" param13="" param14="" param15="" param16="" param17="" param18="" param19="" param2="" param20="" param3="" param4="" param5="" param6="" param7="" param8="" param9="" readonly="false" richCLOB="" showErrors="true" sortIndex="4" sourceType="SELF" submitOnChange="false" type="TEXTFIELD" usageType="" useLabelLeft="true" uuid="8ad80b42-7903-414b-870d-c7f96bfc990c"/>
      <FormComponent created="15.09.2025 09:31:04" descriptor="ANTRAG_VERTRETUNG_NACHNAME" importKey="ANTRAG_VERTRETUNG_NACHNAME" info="" label="" mandatory="true" modified="15.09.2025 09:31:04" param1="" param10="" param11="" param12="" param13="" param14="" param15="" param16="" param17="" param18="" param19="" param2="" param20="" param3="" param4="" param5="" param6="" param7="" param8="" param9="" readonly="false" richCLOB="" showErrors="true" sortIndex="5" sourceType="SELF" submitOnChange="false" type="TEXTFIELD" usageType="" useLabelLeft="true" uuid="5a17d630-28f7-4e1b-875b-c088cfd56b67"/>
      <FormComponent created="15.09.2025 09:31:04" descriptor="ANTRAG_VERTRETUNG_TEL" importKey="ANTRAG_VERTRETUNG_TEL" info="" label="" mandatory="true" modified="15.09.2025 09:31:04" param1="" param10="" param11="" param12="" param13="" param14="" param15="" param16="" param17="" param18="" param19="" param2="" param20="" param3="" param4="" param5="" param6="" param7="" param8="" param9="" readonly="false" richCLOB="" showErrors="true" sortIndex="6" sourceType="SELF" submitOnChange="false" type="TEXTFIELD" usageType="" useLabelLeft="true" uuid="c04b216a-8cf9-42b5-83af-47e691341907"/>
      <FormComponent created="15.09.2025 09:31:04" descriptor="ANTRAG_VERTRETUNG_MAIL" importKey="ANTRAG_VERTRETUNG_MAIL" info="" label="" mandatory="true" modified="15.09.2025 09:31:04" param1="" param10="" param11="" param12="" param13="" param14="" param15="" param16="" param17="" param18="" param19="" param2="" param20="" param3="" param4="" param5="" param6="" param7="" param8="" param9="" readonly="false" richCLOB="" showErrors="true" sortIndex="7" sourceType="SELF" submitOnChange="false" type="TEXTFIELD" usageType="" useLabelLeft="true" uuid="aab6e553-3e47-45a0-98e9-7384ca9315eb"/>
      <FormComponent created="15.09.2025 09:31:04" descriptor="ANTRAG_VERTRETUNG_FUNKTION" importKey="ANTRAG_VERTRETUNG_FUNKTION" info="" label="" mandatory="true" modified="15.09.2025 09:31:04" param1="" param10="" param11="" param12="" param13="" param14="" param15="" param16="" param17="" param18="" param19="" param2="" param20="" param3="" param4="" param5="" param6="" param7="" param8="" param9="" readonly="false" richCLOB="" showErrors="true" sortIndex="8" sourceType="SELF" submitOnChange="false" type="TEXTFIELD" usageType="" useLabelLeft="true" uuid="f39e3cb6-831f-4035-87cf-41667eeca8a4"/>
      <FormComponent created="15.09.2025 09:31:04" descriptor="ANTRAG_VERTRETUNG2_ANREDE" importKey="ANTRAG_VERTRETUNG2_ANREDE" info="" label="" mandatory="false" modified="15.09.2025 09:31:04" param1="" param10="" param11="" param12="" param13="" param14="" param15="" param16="" param17="" param18="" param19="" param2="" param20="" param3="" param4="" param5="" param6="" param7="" param8="" param9="" readonly="false" richCLOB="" showErrors="true" sortIndex="9" sourceType="SELF" submitOnChange="false" type="SELECT_ONE_RADIO_TABLE" usageType="" useLabelLeft="true" uuid="d2c3c739-24d2-40d3-9af5-36c330f6ce82"/>
      <FormComponent created="15.09.2025 09:31:04" descriptor="ANTRAG_VERTRETUNG2_TITEL" importKey="ANTRAG_VERTRETUNG2_TITEL" info="" label="" mandatory="false" modified="15.09.2025 09:31:04" param1="" param10="" param11="" param12="" param13="" param14="" param15="" param16="" param17="" param18="" param19="" param2="" param20="" param3="" param4="" param5="" param6="" param7="" param8="" param9="" readonly="false" richCLOB="" showErrors="true" sortIndex="10" sourceType="SELF" submitOnChange="false" type="TEXTFIELD" usageType="" useLabelLeft="true" uuid="671742ca-56ab-4213-8ce3-cd69598b677c"/>
      <FormComponent created="15.09.2025 09:31:04" descriptor="ANTRAG_VERTRETUNG2_VORNAME" importKey="ANTRAG_VERTRETUNG2_VORNAME" info="" label="" mandatory="false" modified="15.09.2025 09:31:04" param1="" param10="" param11="" param12="" param13="" param14="" param15="" param16="" param17="" param18="" param19="" param2="" param20="" param3="" param4="" param5="" param6="" param7="" param8="" param9="" readonly="false" richCLOB="" showErrors="true" sortIndex="11" sourceType="SELF" submitOnChange="false" type="TEXTFIELD" usageType="" useLabelLeft="true" uuid="804489b8-869d-441e-8768-1ee9aa0b94b6"/>
      <FormComponent created="15.09.2025 09:31:04" descriptor="ANTRAG_VERTRETUNG2_NACHNAME" importKey="ANTRAG_VERTRETUNG2_NACHNAME" info="" label="" mandatory="false" modified="15.09.2025 09:31:04" param1="" param10="" param11="" param12="" param13="" param14="" param15="" param16="" param17="" param18="" param19="" param2="" param20="" param3="" param4="" param5="" param6="" param7="" param8="" param9="" readonly="false" richCLOB="" showErrors="true" sortIndex="12" sourceType="SELF" submitOnChange="false" type="TEXTFIELD" usageType="" useLabelLeft="true" uuid="ec9c990f-8d23-40d8-bff9-db77a0c00cd0"/>
      <FormComponent created="15.09.2025 09:31:04" descriptor="ANTRAG_VERTRETUNG2_TEL" importKey="ANTRAG_VERTRETUNG2_TEL" info="" label="" mandatory="false" modified="15.09.2025 09:31:04" param1="" param10="" param11="" param12="" param13="" param14="" param15="" param16="" param17="" param18="" param19="" param2="" param20="" param3="" param4="" param5="" param6="" param7="" param8="" param9="" readonly="false" richCLOB="" showErrors="true" sortIndex="13" sourceType="SELF" submitOnChange="false" type="TEXTFIELD" usageType="" useLabelLeft="true" uuid="f83db15a-8427-4747-aa04-4ed50002a583"/>
      <FormComponent created="15.09.2025 09:31:04" descriptor="ANTRAG_VERTRETUNG2_MAIL" importKey="ANTRAG_VERTRETUNG2_MAIL" info="" label="" mandatory="false" modified="15.09.2025 09:31:04" param1="" param10="" param11="" param12="" param13="" param14="" param15="" param16="" param17="" param18="" param19="" param2="" param20="" param3="" param4="" param5="" param6="" param7="" param8="" param9="" readonly="false" richCLOB="" showErrors="true" sortIndex="14" sourceType="SELF" submitOnChange="false" type="TEXTFIELD" usageType="" useLabelLeft="true" uuid="1867cc36-db24-4dab-93c5-7c7ea278902c"/>
      <FormComponent created="15.09.2025 09:31:04" descriptor="ANTRAG_VERTRETUNG2_FUNKTION" importKey="ANTRAG_VERTRETUNG2_FUNKTION" info="" label="" mandatory="false" modified="15.09.2025 09:31:04" param1="" param10="" param11="" param12="" param13="" param14="" param15="" param16="" param17="" param18="" param19="" param2="" param20="" param3="" param4="" param5="" param6="" param7="" param8="" param9="" readonly="false" richCLOB="" showErrors="true" sortIndex="15" sourceType="SELF" submitOnChange="false" type="TEXTFIELD" usageType="" useLabelLeft="true" uuid="0b265f02-8632-4028-b81f-1f1aaaedec2d"/>
    </FormDefinition>
  </Webpage>
  <Webpage avoidPagebreak="false" created="10.12.2019 15:01:10" createdBy="Lyonel" guid="e5e52054-55f7-4beb-a867-dfe1ad94b1aa" heading="Zielgruppe / Stunden" hideIfEmpty="false" modified="15.09.2025 09:31:04" modifiedBy="Lyonel" print="" sortIndex="2" uuid="6a0a151e-e5aa-4f30-be57-fc2965c487f6">
    <FormDefinition collapsed="false" created="10.12.2019 15:01:10" createdBy="Lyonel" forPDF="true" forWeb="true" guid="6f794ed5-0299-41d1-8bd4-bd9ebd5e6621" heading="2.1a Zielgruppe Personen (Ankreuzen; Mehrfachnennungen möglich)" modified="15.09.2025 09:31:04" modifiedBy="Lyonel" sortIndex="0" uuid="c9d6b6a7-8c8e-4793-8f47-ef29991cb619" visibility="#GEGENSTAND.LEVEL_CODE# ~ 'BVBO'">
      <FormComponent created="15.09.2025 09:31:04" descriptor="ANTRAG_ZIELGRUPPE_ALT_005" importKey="ANTRAG_ZIELGRUPPE_ALT_005" info="" label=" " mandatory="true" modified="15.09.2025 09:31:04" param1="" param10="" param11="" param12="" param13="" param14="" param15="" param16="" param17="" param18="" param19="" param2="" param20="" param3="" param4="" param5="" param6="ja" param7="" param8="" param9="" readonly="false" richCLOB="" showErrors="true" sortIndex="0" sourceType="SELF" submitOnChange="false" type="SELECT_MANY_CHECKBOX" usageType="" useLabelLeft="false" uuid="79599af8-2db8-4dde-a229-a3351d276ac2"/>
    </FormDefinition>
    <FormDefinition collapsed="false" created="14.06.2022 17:48:18" createdBy="Lyonel" forPDF="true" forWeb="true" guid="7293d146-dee7-4320-9d83-ab5b50c66b8f" heading="2.1b Anzahl geplanter TLN" modified="15.09.2025 09:31:04" modifiedBy="Lyonel" sortIndex="1" uuid="2d64721c-c253-4af1-9453-f631348c6805" visibility="#GEGENSTAND.LEVEL_CODE# ~ 'BVBO'">
      <FormComponent created="15.09.2025 09:31:04" descriptor="MANUELL_TLN_ABBRUCH" importKey="MANUELL_TLN_ABBRUCH" info="" label="Kompetenzfeststellung" mandatory="false" modified="15.09.2025 09:31:04" param1="" param10="" param11="" param12="" param13="" param14="" param15="" param16="" param17="" param18="" param19="" param2="" param20="" param3="" param4="" param5="" param6="" param7="" param8="" param9="" readonly="false" richCLOB="" showErrors="false" sortIndex="0" sourceType="SELF" submitOnChange="false" type="TEXTFIELD" usageType="" useLabelLeft="true" uuid="e9d22a7e-0ac9-4a58-b48f-aacbcc437dcc"/>
      <FormComponent created="15.09.2025 09:31:04" descriptor="MANUELL_TLN_AUSTRITT" importKey="MANUELL_TLN_AUSTRITT" info="" label="Berufsfelderkundung" mandatory="false" modified="15.09.2025 09:31:04" param1="" param10="" param11="" param12="" param13="" param14="" param15="" param16="" param17="" param18="" param19="" param2="" param20="" param3="" param4="" param5="" param6="" param7="" param8="" param9="" readonly="false" richCLOB="" showErrors="false" sortIndex="1" sourceType="SELF" submitOnChange="false" type="TEXTFIELD" usageType="" useLabelLeft="true" uuid="c3adbf9c-b70b-449c-8076-1f506bd1a354"/>
      <FormComponent created="15.09.2025 09:31:04" descriptor="MANUELL_TLN_EINTRITT" importKey="MANUELL_TLN_EINTRITT" info="" label="Vertiefte Praxiserfahrung" mandatory="false" modified="15.09.2025 09:31:04" param1="" param10="" param11="" param12="" param13="" param14="" param15="" param16="" param17="" param18="" param19="" param2="" param20="" param3="" param4="" param5="" param6="" param7="" param8="" param9="" readonly="false" richCLOB="" showErrors="false" sortIndex="2" sourceType="SELF" submitOnChange="false" type="TEXTFIELD" usageType="" useLabelLeft="true" uuid="631b1c53-2fe5-4b14-9209-fa8f6ac6a7b2"/>
      <FormComponent created="15.09.2025 09:31:04" descriptor="MANUELL_TLN_VERBLEIB" importKey="MANUELL_TLN_VERBLEIB" info="" label="Übergang" mandatory="false" modified="15.09.2025 09:31:04" param1="" param10="" param11="" param12="" param13="" param14="" param15="" param16="" param17="" param18="" param19="" param2="" param20="" param3="" param4="" param5="" param6="" param7="" param8="" param9="" readonly="false" richCLOB="" showErrors="false" sortIndex="3" sourceType="SELF" submitOnChange="false" type="TEXTFIELD" usageType="" useLabelLeft="true" uuid="52a1d429-fd33-4fb1-87a9-9632322cec5a"/>
      <FormComponent created="15.09.2025 09:31:04" descriptor="ANZAHL_TLN" importKey="ANZAHL_TLN" info="" label="Anzahl Teilnehmende Gesamt" mandatory="false" modified="15.09.2025 09:31:04" param1="" param10="" param11="" param12="" param13="" param14="" param15="" param16="" param17="" param18="" param19="" param2="" param20="" param3="" param4="" param5="" param6="" param7="" param8="" param9="" readonly="true" richCLOB="" showErrors="false" sortIndex="4" sourceType="SELF" submitOnChange="false" type="TEXTFIELD" usageType="" useLabelLeft="true" uuid="c4a36b65-3687-4d3c-aa71-a141523e20a2"/>
    </FormDefinition>
    <FormDefinition collapsed="false" created="15.06.2022 16:55:52" createdBy="Lyonel" forPDF="true" forWeb="true" guid="6754712b-d52f-4fee-a40c-016f8ca32124" heading="2.2 Qualifizierungsstunden" modified="15.09.2025 09:31:04" modifiedBy="Lyonel" sortIndex="2" uuid="9e384a0a-364d-4438-8cb7-131d0523ba7f" visibility="#GEGENSTAND.LEVEL_CODE# ~ 'BVBO'">
      <FormComponent created="15.09.2025 09:31:04" descriptor="FIXEDTEXT_001" importKey="FIXEDTEXT_001" info="" label="" mandatory="false" modified="15.09.2025 09:31:04" param1="" param10="" param11="" param12="" param13="" param14="" param15="" param16="" param17="" param18="" param19="" param2="" param20="" param3="" param4="" param5="" param6="" param7="" param8="" param9="" readonly="false" richCLOB="&lt;p&gt;&lt;span style=&quot;font-size:12px&quot;&gt;&lt;strong&gt;2.2.1 Stunden je TLN für Praktikum&lt;/strong&gt;&lt;/span&gt;&lt;/p&gt;&#13;&#10;" showErrors="false" sortIndex="0" sourceType="" submitOnChange="false" type="FIXEDRICHTEXT" usageType="" useLabelLeft="false" uuid="79b44bc1-d8eb-4d9d-9561-eba26d00e309"/>
      <FormComponent created="15.09.2025 09:31:04" descriptor="PH_ZAHL_006" importKey="PH_ZAHL_006" info="" label="Kompetenzfeststellung" mandatory="false" modified="15.09.2025 09:31:04" param1="" param10="" param11="" param12="" param13="" param14="" param15="" param16="" param17="" param18="" param19="" param2="" param20="" param3="" param4="" param5="" param6="HOUR_MAX_H" param7="" param8="" param9="" readonly="false" richCLOB="" showErrors="false" sortIndex="1" sourceType="SELF" submitOnChange="false" type="TEXTFIELD" usageType="" useLabelLeft="true" uuid="d857c509-2fd7-48c8-a92f-b5d8d1bb0fbf"/>
      <FormComponent created="15.09.2025 09:31:04" descriptor="PH_ZAHL_007" importKey="PH_ZAHL_007" info="" label="Berufsfelderkundung" mandatory="false" modified="15.09.2025 09:31:04" param1="" param10="" param11="" param12="" param13="" param14="" param15="" param16="" param17="" param18="" param19="" param2="" param20="" param3="" param4="" param5="" param6="HOUR_MAX_H" param7="" param8="" param9="" readonly="false" richCLOB="" showErrors="false" sortIndex="2" sourceType="SELF" submitOnChange="false" type="TEXTFIELD" usageType="" useLabelLeft="true" uuid="f4e41b1d-a272-4321-91cb-3973c6235685"/>
      <FormComponent created="15.09.2025 09:31:04" descriptor="PH_ZAHL_008" importKey="PH_ZAHL_008" info="" label="Vertiefte Praxiserfahrung" mandatory="false" modified="15.09.2025 09:31:04" param1="" param10="" param11="" param12="" param13="" param14="" param15="" param16="" param17="" param18="" param19="" param2="" param20="" param3="" param4="" param5="" param6="HOUR_MAX_H" param7="" param8="" param9="" readonly="false" richCLOB="" showErrors="false" sortIndex="3" sourceType="SELF" submitOnChange="false" type="TEXTFIELD" usageType="" useLabelLeft="true" uuid="a80b3f5a-bf4e-459c-b154-61ffa96d43ca"/>
      <FormComponent created="15.09.2025 09:31:04" descriptor="PH_ZAHL_009" importKey="PH_ZAHL_009" info="" label="Übergang" mandatory="false" modified="15.09.2025 09:31:04" param1="" param10="" param11="" param12="" param13="" param14="" param15="" param16="" param17="" param18="" param19="" param2="" param20="" param3="" param4="" param5="" param6="HOUR_MAX_H" param7="" param8="" param9="" readonly="false" richCLOB="" showErrors="false" sortIndex="4" sourceType="SELF" submitOnChange="false" type="TEXTFIELD" usageType="" useLabelLeft="true" uuid="9c9e82e3-c9b1-4587-85a5-085a622a241d"/>
      <FormComponent created="15.09.2025 09:31:04" descriptor="TLN_ANZAHL_QUALISTUNDEN_PRAKTIKUM" importKey="TLN_ANZAHL_QUALISTUNDEN_PRAKTIKUM" info="" label="Stunden je TLN für Praktikum Gesamt" mandatory="false" modified="15.09.2025 09:31:04" param1="" param10="" param11="" param12="" param13="" param14="" param15="" param16="" param17="" param18="" param19="" param2="" param20="" param3="" param4="" param5="" param6="HOUR_MAX_H" param7="" param8="" param9="" readonly="true" richCLOB="" showErrors="false" sortIndex="5" sourceType="SELF" submitOnChange="false" type="TEXTFIELD" usageType="" useLabelLeft="true" uuid="674436af-e702-44b2-b6c2-cbc757ce63b6"/>
      <FormComponent created="15.09.2025 09:31:04" descriptor="FIXEDTEXT_001" importKey="FIXEDTEXT_001" info="" label="" mandatory="false" modified="15.09.2025 09:31:04" param1="" param10="" param11="" param12="" param13="" param14="" param15="" param16="" param17="" param18="" param19="" param2="" param20="" param3="" param4="" param5="" param6="" param7="" param8="" param9="" readonly="false" richCLOB="&lt;p&gt;&lt;span style=&quot;font-size:12px&quot;&gt;&lt;strong&gt;2.2.2&amp;nbsp;Stunden je TLN für Theorie&lt;/strong&gt;&lt;/span&gt;&lt;/p&gt;&#13;&#10;" showErrors="false" sortIndex="6" sourceType="" submitOnChange="false" type="FIXEDRICHTEXT" usageType="" useLabelLeft="false" uuid="b41c78f4-3296-407e-a5ef-689fb547eb44"/>
      <FormComponent created="15.09.2025 09:31:04" descriptor="PH_ZAHL_010" importKey="PH_ZAHL_010" info="" label="Kompetenzfeststellung" mandatory="false" modified="15.09.2025 09:31:04" param1="" param10="" param11="" param12="" param13="" param14="" param15="" param16="" param17="" param18="" param19="" param2="" param20="" param3="" param4="" param5="" param6="HOUR_MAX_H" param7="" param8="" param9="" readonly="false" richCLOB="" showErrors="false" sortIndex="7" sourceType="SELF" submitOnChange="false" type="TEXTFIELD" usageType="" useLabelLeft="true" uuid="05c5a411-56a9-4ea8-ad9d-e0c185e12db1"/>
      <FormComponent created="15.09.2025 09:31:04" descriptor="PH_ZAHL_011" importKey="PH_ZAHL_011" info="" label="Berufsfelderkundung" mandatory="false" modified="15.09.2025 09:31:04" param1="" param10="" param11="" param12="" param13="" param14="" param15="" param16="" param17="" param18="" param19="" param2="" param20="" param3="" param4="" param5="" param6="HOUR_MAX_H" param7="" param8="" param9="" readonly="false" richCLOB="" showErrors="false" sortIndex="8" sourceType="SELF" submitOnChange="false" type="TEXTFIELD" usageType="" useLabelLeft="true" uuid="0b81787e-9d5b-4ca1-9dfd-3399ff6eed4d"/>
      <FormComponent created="15.09.2025 09:31:04" descriptor="PH_ZAHL_012" importKey="PH_ZAHL_012" info="" label="Vertiefte Praxiserfahrung" mandatory="false" modified="15.09.2025 09:31:04" param1="" param10="" param11="" param12="" param13="" param14="" param15="" param16="" param17="" param18="" param19="" param2="" param20="" param3="" param4="" param5="" param6="HOUR_MAX_H" param7="" param8="" param9="" readonly="false" richCLOB="" showErrors="false" sortIndex="9" sourceType="SELF" submitOnChange="false" type="TEXTFIELD" usageType="" useLabelLeft="true" uuid="4f89c4b6-d99b-4f6b-b364-eb9d78660e25"/>
      <FormComponent created="15.09.2025 09:31:04" descriptor="PH_ZAHL_013" importKey="PH_ZAHL_013" info="" label="Übergang" mandatory="false" modified="15.09.2025 09:31:04" param1="" param10="" param11="" param12="" param13="" param14="" param15="" param16="" param17="" param18="" param19="" param2="" param20="" param3="" param4="" param5="" param6="HOUR_MAX_H" param7="" param8="" param9="" readonly="false" richCLOB="" showErrors="false" sortIndex="10" sourceType="SELF" submitOnChange="false" type="TEXTFIELD" usageType="" useLabelLeft="true" uuid="d7be8ada-d557-4a26-bc34-5ef4352c3a50"/>
      <FormComponent created="15.09.2025 09:31:04" descriptor="TLN_ANZAHL_QUALISTUNDEN_THEORIE" importKey="TLN_ANZAHL_QUALISTUNDEN_THEORIE" info="" label="Stunden je TLN für Theorie Gesamt" mandatory="false" modified="15.09.2025 09:31:04" param1="" param10="" param11="" param12="" param13="" param14="" param15="" param16="" param17="" param18="" param19="" param2="" param20="" param3="" param4="" param5="" param6="HOUR_MAX_H" param7="" param8="" param9="" readonly="true" richCLOB="" showErrors="false" sortIndex="11" sourceType="SELF" submitOnChange="false" type="TEXTFIELD" usageType="" useLabelLeft="true" uuid="facaa02f-7634-4ec6-8660-e7dcb09cf799"/>
      <FormComponent created="15.09.2025 09:31:04" descriptor="FIXEDTEXT_001" importKey="FIXEDTEXT_001" info="" label="" mandatory="false" modified="15.09.2025 09:31:04" param1="" param10="" param11="" param12="" param13="" param14="" param15="" param16="" param17="" param18="" param19="" param2="" param20="" param3="" param4="" param5="" param6="" param7="" param8="" param9="" readonly="false" richCLOB="&lt;p&gt;&lt;span style=&quot;font-size:12px&quot;&gt;&lt;strong&gt;2.2.3&amp;nbsp;Stunden&amp;nbsp;Gesamt&lt;/strong&gt;&lt;/span&gt;&lt;/p&gt;&#13;&#10;" showErrors="false" sortIndex="12" sourceType="" submitOnChange="false" type="FIXEDRICHTEXT" usageType="" useLabelLeft="false" uuid="18e06cfd-9411-44c0-8526-9ae063d40f3d"/>
      <FormComponent created="15.09.2025 09:31:04" descriptor="PH_ZAHL_005" importKey="PH_ZAHL_005" info="" label="" mandatory="false" modified="15.09.2025 09:31:04" param1="" param10="" param11="" param12="" param13="" param14="" param15="" param16="" param17="" param18="" param19="" param2="" param20="" param3="" param4="" param5="" param6="" param7="" param8="" param9="" readonly="false" richCLOB="" showErrors="false" sortIndex="13" sourceType="SELF" submitOnChange="false" type="DISPLAYER" usageType="" useLabelLeft="true" uuid="dab36aa1-d69d-4d2a-850f-56238725aa16"/>
      <FormComponent created="15.09.2025 09:31:04" descriptor="ANZAHL_TLN_STUNDEN" importKey="ANZAHL_TLN_STUNDEN" info="" label="" mandatory="false" modified="15.09.2025 09:31:04" param1="" param10="" param11="" param12="" param13="" param14="" param15="" param16="" param17="" param18="" param19="" param2="" param20="" param3="" param4="" param5="" param6="" param7="" param8="" param9="" readonly="false" richCLOB="" showErrors="true" sortIndex="14" sourceType="SELF" submitOnChange="false" type="TEXTFIELD_PER_YEAR" usageType="" useLabelLeft="true" uuid="977ff913-d67d-4e9c-83dd-574fe469d842"/>
    </FormDefinition>
  </Webpage>
  <Webpage avoidPagebreak="false" created="10.12.2019 15:01:10" createdBy="Lyonel" guid="fc30e5f0-16e5-4831-bbda-33af74c620c3" heading="Finanzierung des Projekts" hideIfEmpty="false" modified="15.09.2025 09:31:04" modifiedBy="Lyonel" print="" sortIndex="3" uuid="08780d83-b14f-4be0-96bf-3e2b18dbd2ee">
    <FormDefinition collapsed="false" created="10.12.2019 15:01:10" createdBy="Lyonel" forPDF="true" forWeb="true" guid="1ef1b26f-868d-44bd-ab1c-7c3d02f4d467" heading="4.3 Finanzierung des Projekts/geplante Gesamteinnahmen" modified="15.09.2025 09:31:04" modifiedBy="Lyonel" sortIndex="0" uuid="3ff7d07e-afe5-467d-80b4-ce0b55199a34" visibility="">
      <FormComponent created="15.09.2025 09:31:04" descriptor="FINANCE_4_3" importKey="FINANCE_4_3" info="" label=" " mandatory="false" modified="15.09.2025 09:31:04" param1="" param10="" param11="" param12="" param13="" param14="" param15="" param16="" param17="" param18="" param19="" param2="" param20="" param3="0" param4="" param5="" param6="" param7="" param8="" param9="" readonly="true" richCLOB="" showErrors="true" sortIndex="0" sourceType="SELF" submitOnChange="false" type="FINANCE" usageType="" useLabelLeft="false" uuid="cfaeb6a6-486c-4bd5-83e4-eb7030065f1e"/>
      <FormComponent created="15.09.2025 09:31:04" descriptor="FINANCE_4_3_1_1" importKey="FINANCE_4_3_1_1" info="" label=" " mandatory="false" modified="15.09.2025 09:31:04" param1="" param10="ja" param11="" param12="" param13="" param14="" param15="" param16="" param17="" param18="" param19="" param2="" param20="" param3="0" param4="ja" param5="" param6="" param7="" param8="" param9="" readonly="false" richCLOB="" showErrors="true" sortIndex="1" sourceType="SELF" submitOnChange="false" type="FINANCE" usageType="" useLabelLeft="false" uuid="9842b3a1-3c30-466a-8d5c-a473e150ede1"/>
      <FormComponent created="15.09.2025 09:31:04" descriptor="FINANCE_4_3_1_3" importKey="FINANCE_4_3_1_3" info="" label=" " mandatory="false" modified="15.09.2025 09:31:04" param1="" param10="ja" param11="" param12="" param13="" param14="" param15="" param16="" param17="" param18="" param19="" param2="" param20="" param3="0" param4="ja" param5="" param6="" param7="" param8="" param9="" readonly="false" richCLOB="" showErrors="true" sortIndex="2" sourceType="SELF" submitOnChange="false" type="FINANCE" usageType="" useLabelLeft="false" uuid="e4958a34-680a-4990-a9b3-db1a47830d36"/>
    </FormDefinition>
  </Webpage>
  <Webpage avoidPagebreak="false" created="10.12.2019 15:01:10" createdBy="Lyonel" guid="6863aaea-5656-46ea-b4d0-e46ddb1ea89a" heading="Projektbeschreibung" hideIfEmpty="false" modified="15.09.2025 09:31:04" modifiedBy="Lyonel" print="" sortIndex="4" uuid="e1e693ac-fe8e-4ad2-9796-6d17095a771f">
    <FormDefinition collapsed="false" created="16.06.2022 14:23:27" createdBy="Lyonel" forPDF="true" forWeb="true" guid="af91dd3c-e926-4e54-af95-b6b5f820d3fd" heading="5 Projektbeschreibung" modified="15.09.2025 09:31:04" modifiedBy="Lyonel" sortIndex="0" uuid="ab036da6-7735-47fd-b314-80f4aeeedd41" visibility="">
      <FormComponent created="15.09.2025 09:31:04" descriptor="FIXEDTEXT_001" importKey="FIXEDTEXT_001" info="" label="" mandatory="false" modified="15.09.2025 09:31:04" param1="" param10="" param11="" param12="" param13="" param14="" param15="" param16="" param17="" param18="" param19="" param2="" param20="" param3="" param4="" param5="" param6="" param7="" param8="" param9="" readonly="false" richCLOB="&lt;p&gt;&lt;strong&gt;5.1 Welche Module des Landesprogramms BVBO werden im Rahmen dieses Projekts in welchen Jahrgangsstufen&amp;nbsp;genutzt? ..&amp;nbsp;in Stunden pro TLN&lt;/strong&gt;&lt;/p&gt;&#13;&#10;" showErrors="false" sortIndex="0" sourceType="" submitOnChange="false" type="FIXEDRICHTEXT" usageType="" useLabelLeft="false" uuid="6a1e84da-91ef-4e70-87d4-4bcc707c604a"/>
    </FormDefinition>
    <FormDefinition collapsed="false" created="16.06.2022 14:59:49" createdBy="Lyonel" forPDF="true" forWeb="true" guid="47943452-b7d6-4dce-8cf9-0f2bfaef26f2" heading="" modified="15.09.2025 09:31:04" modifiedBy="Lyonel" sortIndex="1" uuid="09d6b354-4518-4ef2-b886-9b3b4b4f7749" visibility="#BILDUNG_JAHRGANGSSTUFE# == '7. Klasse'">
      <FormComponent created="15.09.2025 09:31:04" descriptor="FIXEDTEXT_001" importKey="FIXEDTEXT_001" info="" label="" mandatory="false" modified="15.09.2025 09:31:04" param1="" param10="" param11="" param12="" param13="" param14="" param15="" param16="" param17="" param18="" param19="" param2="" param20="" param3="" param4="" param5="" param6="" param7="" param8="" param9="" readonly="false" richCLOB="&lt;p&gt;&lt;strong&gt;Jahrgangsstufe 7&lt;/strong&gt;&lt;/p&gt;&#13;&#10;" showErrors="false" sortIndex="0" sourceType="" submitOnChange="false" type="FIXEDRICHTEXT" usageType="" useLabelLeft="false" uuid="bfa11d23-f88b-4a9e-abed-d8f708d68f1f"/>
      <FormComponent created="15.09.2025 09:31:04" descriptor="TLN_STUNDEN_MODUL_01" importKey="TLN_STUNDEN_MODUL_01" info="" label="Kompetenzfeststellung" mandatory="false" modified="15.09.2025 09:31:04" param1="" param10="" param11="" param12="" param13="" param14="" param15="" param16="" param17="" param18="" param19="" param2="" param20="" param3="" param4="" param5="" param6="" param7="" param8="" param9="" readonly="false" richCLOB="" showErrors="false" sortIndex="1" sourceType="SELF" submitOnChange="false" type="TEXTFIELD" usageType="FLEX_1" useLabelLeft="true" uuid="a1129562-0750-435d-83fc-f4da216afbde"/>
      <FormComponent created="15.09.2025 09:31:04" descriptor="TLN_STUNDEN_MODUL_02" importKey="TLN_STUNDEN_MODUL_02" info="" label="Berufsfelderkundung" mandatory="false" modified="15.09.2025 09:31:04" param1="" param10="" param11="" param12="" param13="" param14="" param15="" param16="" param17="" param18="" param19="" param2="" param20="" param3="" param4="" param5="" param6="" param7="" param8="" param9="" readonly="false" richCLOB="" showErrors="false" sortIndex="2" sourceType="SELF" submitOnChange="false" type="TEXTFIELD" usageType="FLEX_1" useLabelLeft="true" uuid="85f247c3-c199-4daf-894a-9f1dde892396"/>
      <FormComponent created="15.09.2025 09:31:04" descriptor="TLN_STUNDEN_MODUL_03" importKey="TLN_STUNDEN_MODUL_03" info="" label="Vertiefte Praxiserfahrung" mandatory="false" modified="15.09.2025 09:31:04" param1="" param10="" param11="" param12="" param13="" param14="" param15="" param16="" param17="" param18="" param19="" param2="" param20="" param3="" param4="" param5="" param6="" param7="" param8="" param9="" readonly="false" richCLOB="" showErrors="false" sortIndex="3" sourceType="SELF" submitOnChange="false" type="TEXTFIELD" usageType="FLEX_1" useLabelLeft="true" uuid="f27eaeaf-79fd-47b2-b882-7c8e9bfc4835"/>
      <FormComponent created="15.09.2025 09:31:04" descriptor="TLN_STUNDEN_MODUL_04" importKey="TLN_STUNDEN_MODUL_04" info="" label="Übergang" mandatory="false" modified="15.09.2025 09:31:04" param1="" param10="" param11="" param12="" param13="" param14="" param15="" param16="" param17="" param18="" param19="" param2="" param20="" param3="" param4="" param5="" param6="" param7="" param8="" param9="" readonly="false" richCLOB="" showErrors="false" sortIndex="4" sourceType="SELF" submitOnChange="false" type="TEXTFIELD" usageType="FLEX_1" useLabelLeft="true" uuid="36287b6c-9c41-489b-bb3a-737871fa0d9c"/>
    </FormDefinition>
    <FormDefinition collapsed="false" created="16.06.2022 14:59:52" createdBy="Lyonel" forPDF="true" forWeb="true" guid="529027e7-3e28-43bc-b040-57d783e89573" heading="" modified="15.09.2025 09:31:04" modifiedBy="Lyonel" sortIndex="2" uuid="bfcb3dc6-84af-4fc8-adde-570c35f32d67" visibility="#BILDUNG_JAHRGANGSSTUFE# == '8. Klasse'">
      <FormComponent created="15.09.2025 09:31:04" descriptor="FIXEDTEXT_001" importKey="FIXEDTEXT_001" info="" label="" mandatory="false" modified="15.09.2025 09:31:04" param1="" param10="" param11="" param12="" param13="" param14="" param15="" param16="" param17="" param18="" param19="" param2="" param20="" param3="" param4="" param5="" param6="" param7="" param8="" param9="" readonly="false" richCLOB="&lt;p&gt;&lt;strong&gt;Jahrgangsstufe 8&lt;/strong&gt;&lt;/p&gt;&#13;&#10;" showErrors="false" sortIndex="0" sourceType="" submitOnChange="false" type="FIXEDRICHTEXT" usageType="" useLabelLeft="false" uuid="c462846e-2880-4849-a4ac-029c3781a0d2"/>
      <FormComponent created="15.09.2025 09:31:04" descriptor="TLN_STUNDEN_MODUL_01" importKey="TLN_STUNDEN_MODUL_01" info="" label="Kompetenzfeststellung" mandatory="false" modified="15.09.2025 09:31:04" param1="" param10="" param11="" param12="" param13="" param14="" param15="" param16="" param17="" param18="" param19="" param2="" param20="" param3="" param4="" param5="" param6="" param7="" param8="" param9="" readonly="false" richCLOB="" showErrors="false" sortIndex="1" sourceType="SELF" submitOnChange="false" type="TEXTFIELD" usageType="FLEX_2" useLabelLeft="true" uuid="29ee18ae-a5a6-4668-92a0-840625a4f686"/>
      <FormComponent created="15.09.2025 09:31:04" descriptor="TLN_STUNDEN_MODUL_02" importKey="TLN_STUNDEN_MODUL_02" info="" label="Berufsfelderkundung" mandatory="false" modified="15.09.2025 09:31:04" param1="" param10="" param11="" param12="" param13="" param14="" param15="" param16="" param17="" param18="" param19="" param2="" param20="" param3="" param4="" param5="" param6="" param7="" param8="" param9="" readonly="false" richCLOB="" showErrors="false" sortIndex="2" sourceType="SELF" submitOnChange="false" type="TEXTFIELD" usageType="FLEX_2" useLabelLeft="true" uuid="30539bfd-8f3d-4f91-98f8-eede9fc9a0f0"/>
      <FormComponent created="15.09.2025 09:31:04" descriptor="TLN_STUNDEN_MODUL_03" importKey="TLN_STUNDEN_MODUL_03" info="" label="Vertiefte Praxiserfahrung" mandatory="false" modified="15.09.2025 09:31:04" param1="" param10="" param11="" param12="" param13="" param14="" param15="" param16="" param17="" param18="" param19="" param2="" param20="" param3="" param4="" param5="" param6="" param7="" param8="" param9="" readonly="false" richCLOB="" showErrors="false" sortIndex="3" sourceType="SELF" submitOnChange="false" type="TEXTFIELD" usageType="FLEX_2" useLabelLeft="true" uuid="9ab76f6e-c6e2-4ed1-bdc0-bd21a2bd4d94"/>
      <FormComponent created="15.09.2025 09:31:04" descriptor="TLN_STUNDEN_MODUL_04" importKey="TLN_STUNDEN_MODUL_04" info="" label="Übergang" mandatory="false" modified="15.09.2025 09:31:04" param1="" param10="" param11="" param12="" param13="" param14="" param15="" param16="" param17="" param18="" param19="" param2="" param20="" param3="" param4="" param5="" param6="" param7="" param8="" param9="" readonly="false" richCLOB="" showErrors="false" sortIndex="4" sourceType="SELF" submitOnChange="false" type="TEXTFIELD" usageType="FLEX_2" useLabelLeft="true" uuid="fa58f2c6-f51d-4c22-860c-6fcde281c77d"/>
    </FormDefinition>
    <FormDefinition collapsed="false" created="16.06.2022 14:59:56" createdBy="Lyonel" forPDF="true" forWeb="true" guid="58042541-9cde-4a63-83b3-082d584c30c3" heading="" modified="15.09.2025 09:31:04" modifiedBy="Lyonel" sortIndex="3" uuid="dd89a0f1-b011-4689-99b5-505dc63a40b1" visibility="#BILDUNG_JAHRGANGSSTUFE# == '9. Klasse'">
      <FormComponent created="15.09.2025 09:31:04" descriptor="FIXEDTEXT_001" importKey="FIXEDTEXT_001" info="" label="" mandatory="false" modified="15.09.2025 09:31:04" param1="" param10="" param11="" param12="" param13="" param14="" param15="" param16="" param17="" param18="" param19="" param2="" param20="" param3="" param4="" param5="" param6="" param7="" param8="" param9="" readonly="false" richCLOB="&lt;p&gt;&lt;strong&gt;Jahrgangsstufe 9&lt;/strong&gt;&lt;/p&gt;&#13;&#10;" showErrors="false" sortIndex="0" sourceType="" submitOnChange="false" type="FIXEDRICHTEXT" usageType="" useLabelLeft="false" uuid="194aa9d0-5639-4b94-8c4a-d41db675d520"/>
      <FormComponent created="15.09.2025 09:31:04" descriptor="TLN_STUNDEN_MODUL_01" importKey="TLN_STUNDEN_MODUL_01" info="" label="Kompetenzfeststellung" mandatory="false" modified="15.09.2025 09:31:04" param1="" param10="" param11="" param12="" param13="" param14="" param15="" param16="" param17="" param18="" param19="" param2="" param20="" param3="" param4="" param5="" param6="" param7="" param8="" param9="" readonly="false" richCLOB="" showErrors="false" sortIndex="1" sourceType="SELF" submitOnChange="false" type="TEXTFIELD" usageType="FLEX_3" useLabelLeft="true" uuid="89bf9899-6b04-4988-9e5b-0955797c4b05"/>
      <FormComponent created="15.09.2025 09:31:05" descriptor="TLN_STUNDEN_MODUL_02" importKey="TLN_STUNDEN_MODUL_02" info="" label="Berufsfelderkundung" mandatory="false" modified="15.09.2025 09:31:05" param1="" param10="" param11="" param12="" param13="" param14="" param15="" param16="" param17="" param18="" param19="" param2="" param20="" param3="" param4="" param5="" param6="" param7="" param8="" param9="" readonly="false" richCLOB="" showErrors="false" sortIndex="2" sourceType="SELF" submitOnChange="false" type="TEXTFIELD" usageType="FLEX_3" useLabelLeft="true" uuid="01ec7ff0-ab67-402d-9cc8-6de3c7f5a2a4"/>
      <FormComponent created="15.09.2025 09:31:05" descriptor="TLN_STUNDEN_MODUL_03" importKey="TLN_STUNDEN_MODUL_03" info="" label="Vertiefte Praxiserfahrung" mandatory="false" modified="15.09.2025 09:31:05" param1="" param10="" param11="" param12="" param13="" param14="" param15="" param16="" param17="" param18="" param19="" param2="" param20="" param3="" param4="" param5="" param6="" param7="" param8="" param9="" readonly="false" richCLOB="" showErrors="false" sortIndex="3" sourceType="SELF" submitOnChange="false" type="TEXTFIELD" usageType="FLEX_3" useLabelLeft="true" uuid="a4bdd953-a01b-40e7-aaf9-7f5af488df12"/>
      <FormComponent created="15.09.2025 09:31:05" descriptor="TLN_STUNDEN_MODUL_04" importKey="TLN_STUNDEN_MODUL_04" info="" label="Übergang" mandatory="false" modified="15.09.2025 09:31:05" param1="" param10="" param11="" param12="" param13="" param14="" param15="" param16="" param17="" param18="" param19="" param2="" param20="" param3="" param4="" param5="" param6="" param7="" param8="" param9="" readonly="false" richCLOB="" showErrors="false" sortIndex="4" sourceType="SELF" submitOnChange="false" type="TEXTFIELD" usageType="FLEX_3" useLabelLeft="true" uuid="7c53998e-3feb-4521-a660-6edf953d8359"/>
    </FormDefinition>
    <FormDefinition collapsed="false" created="16.06.2022 14:59:59" createdBy="Lyonel" forPDF="true" forWeb="true" guid="560fe7f3-0c4a-4405-9357-4e47ac4dd957" heading="" modified="15.09.2025 09:31:05" modifiedBy="Lyonel" sortIndex="4" uuid="5b51b6b5-ba07-425b-8057-9e88865a6c6c" visibility="#BILDUNG_JAHRGANGSSTUFE# == '10. Klasse'">
      <FormComponent created="15.09.2025 09:31:05" descriptor="FIXEDTEXT_001" importKey="FIXEDTEXT_001" info="" label="" mandatory="false" modified="15.09.2025 09:31:05" param1="" param10="" param11="" param12="" param13="" param14="" param15="" param16="" param17="" param18="" param19="" param2="" param20="" param3="" param4="" param5="" param6="" param7="" param8="" param9="" readonly="false" richCLOB="&lt;p&gt;&lt;strong&gt;Jahrgangsstufe 10&lt;/strong&gt;&lt;/p&gt;&#13;&#10;" showErrors="false" sortIndex="0" sourceType="" submitOnChange="false" type="FIXEDRICHTEXT" usageType="" useLabelLeft="false" uuid="597ef396-a98f-4626-9cd2-408aa327a4bd"/>
      <FormComponent created="15.09.2025 09:31:05" descriptor="TLN_STUNDEN_MODUL_01" importKey="TLN_STUNDEN_MODUL_01" info="" label="Kompetenzfeststellung" mandatory="false" modified="15.09.2025 09:31:05" param1="" param10="" param11="" param12="" param13="" param14="" param15="" param16="" param17="" param18="" param19="" param2="" param20="" param3="" param4="" param5="" param6="" param7="" param8="" param9="" readonly="false" richCLOB="" showErrors="false" sortIndex="1" sourceType="SELF" submitOnChange="false" type="TEXTFIELD" usageType="FLEX_4" useLabelLeft="true" uuid="8a2899f2-5d1f-49bc-9ab1-e7e269c204b5"/>
      <FormComponent created="15.09.2025 09:31:05" descriptor="TLN_STUNDEN_MODUL_02" importKey="TLN_STUNDEN_MODUL_02" info="" label="Berufsfelderkundung" mandatory="false" modified="15.09.2025 09:31:05" param1="" param10="" param11="" param12="" param13="" param14="" param15="" param16="" param17="" param18="" param19="" param2="" param20="" param3="" param4="" param5="" param6="" param7="" param8="" param9="" readonly="false" richCLOB="" showErrors="false" sortIndex="2" sourceType="SELF" submitOnChange="false" type="TEXTFIELD" usageType="FLEX_4" useLabelLeft="true" uuid="a31234ec-82ac-4bae-8ed5-5015e90283c4"/>
      <FormComponent created="15.09.2025 09:31:05" descriptor="TLN_STUNDEN_MODUL_03" importKey="TLN_STUNDEN_MODUL_03" info="" label="Vertiefte Praxiserfahrung" mandatory="false" modified="15.09.2025 09:31:05" param1="" param10="" param11="" param12="" param13="" param14="" param15="" param16="" param17="" param18="" param19="" param2="" param20="" param3="" param4="" param5="" param6="" param7="" param8="" param9="" readonly="false" richCLOB="" showErrors="false" sortIndex="3" sourceType="SELF" submitOnChange="false" type="TEXTFIELD" usageType="FLEX_4" useLabelLeft="true" uuid="bc14e007-295b-46c0-8174-f25bde7a254f"/>
      <FormComponent created="15.09.2025 09:31:05" descriptor="TLN_STUNDEN_MODUL_04" importKey="TLN_STUNDEN_MODUL_04" info="" label="Übergang" mandatory="false" modified="15.09.2025 09:31:05" param1="" param10="" param11="" param12="" param13="" param14="" param15="" param16="" param17="" param18="" param19="" param2="" param20="" param3="" param4="" param5="" param6="" param7="" param8="" param9="" readonly="false" richCLOB="" showErrors="false" sortIndex="4" sourceType="SELF" submitOnChange="false" type="TEXTFIELD" usageType="FLEX_4" useLabelLeft="true" uuid="7677a698-e778-4b6a-afe6-0c91deeff8c6"/>
    </FormDefinition>
    <FormDefinition collapsed="false" created="16.06.2022 15:00:03" createdBy="Lyonel" forPDF="true" forWeb="true" guid="bda53164-2913-4356-b568-f34329a0d517" heading="" modified="15.09.2025 09:31:05" modifiedBy="Lyonel" sortIndex="5" uuid="24a889ce-2af5-4b3d-be71-ac45338fd945" visibility="#BILDUNG_JAHRGANGSSTUFE# == '11. Klasse'">
      <FormComponent created="15.09.2025 09:31:05" descriptor="FIXEDTEXT_001" importKey="FIXEDTEXT_001" info="" label="" mandatory="false" modified="15.09.2025 09:31:05" param1="" param10="" param11="" param12="" param13="" param14="" param15="" param16="" param17="" param18="" param19="" param2="" param20="" param3="" param4="" param5="" param6="" param7="" param8="" param9="" readonly="false" richCLOB="&lt;p&gt;&lt;strong&gt;Jahrgangsstufe 11&lt;/strong&gt;&lt;/p&gt;&#13;&#10;" showErrors="false" sortIndex="0" sourceType="" submitOnChange="false" type="FIXEDRICHTEXT" usageType="" useLabelLeft="false" uuid="beecc0b8-a941-45c6-bcd1-eb6a56fa3c7e"/>
      <FormComponent created="15.09.2025 09:31:05" descriptor="TLN_STUNDEN_MODUL_01" importKey="TLN_STUNDEN_MODUL_01" info="" label="Kompetenzfeststellung" mandatory="false" modified="15.09.2025 09:31:05" param1="" param10="" param11="" param12="" param13="" param14="" param15="" param16="" param17="" param18="" param19="" param2="" param20="" param3="" param4="" param5="" param6="" param7="" param8="" param9="" readonly="false" richCLOB="" showErrors="false" sortIndex="1" sourceType="SELF" submitOnChange="false" type="TEXTFIELD" usageType="FLEX_5" useLabelLeft="true" uuid="78589bb1-7a6c-4da0-ba58-68c8e6984d25"/>
      <FormComponent created="15.09.2025 09:31:05" descriptor="TLN_STUNDEN_MODUL_02" importKey="TLN_STUNDEN_MODUL_02" info="" label="Berufsfelderkundung" mandatory="false" modified="15.09.2025 09:31:05" param1="" param10="" param11="" param12="" param13="" param14="" param15="" param16="" param17="" param18="" param19="" param2="" param20="" param3="" param4="" param5="" param6="" param7="" param8="" param9="" readonly="false" richCLOB="" showErrors="false" sortIndex="2" sourceType="SELF" submitOnChange="false" type="TEXTFIELD" usageType="FLEX_5" useLabelLeft="true" uuid="d52860e8-3e98-4335-83b5-2899d37ad769"/>
      <FormComponent created="15.09.2025 09:31:05" descriptor="TLN_STUNDEN_MODUL_03" importKey="TLN_STUNDEN_MODUL_03" info="" label="Vertiefte Praxiserfahrung" mandatory="false" modified="15.09.2025 09:31:05" param1="" param10="" param11="" param12="" param13="" param14="" param15="" param16="" param17="" param18="" param19="" param2="" param20="" param3="" param4="" param5="" param6="" param7="" param8="" param9="" readonly="false" richCLOB="" showErrors="false" sortIndex="3" sourceType="SELF" submitOnChange="false" type="TEXTFIELD" usageType="FLEX_5" useLabelLeft="true" uuid="2821b07f-f316-424e-8782-1977b19f307b"/>
      <FormComponent created="15.09.2025 09:31:05" descriptor="TLN_STUNDEN_MODUL_04" importKey="TLN_STUNDEN_MODUL_04" info="" label="Übergang" mandatory="false" modified="15.09.2025 09:31:05" param1="" param10="" param11="" param12="" param13="" param14="" param15="" param16="" param17="" param18="" param19="" param2="" param20="" param3="" param4="" param5="" param6="" param7="" param8="" param9="" readonly="false" richCLOB="" showErrors="false" sortIndex="4" sourceType="SELF" submitOnChange="false" type="TEXTFIELD" usageType="FLEX_5" useLabelLeft="true" uuid="b92b32f7-6eef-4034-8541-9d6d6ac7721a"/>
    </FormDefinition>
    <FormDefinition collapsed="false" created="16.06.2022 15:00:06" createdBy="Lyonel" forPDF="true" forWeb="true" guid="1710a107-e866-49ec-9ec1-ef41ca2717cd" heading="" modified="15.09.2025 09:31:05" modifiedBy="Lyonel" sortIndex="6" uuid="af57f228-c118-4ba7-976f-d0757d5c0e1e" visibility="#BILDUNG_JAHRGANGSSTUFE# == '12. Klasse'">
      <FormComponent created="15.09.2025 09:31:05" descriptor="FIXEDTEXT_001" importKey="FIXEDTEXT_001" info="" label="" mandatory="false" modified="15.09.2025 09:31:05" param1="" param10="" param11="" param12="" param13="" param14="" param15="" param16="" param17="" param18="" param19="" param2="" param20="" param3="" param4="" param5="" param6="" param7="" param8="" param9="" readonly="false" richCLOB="&lt;p&gt;&lt;strong&gt;Jahrgangsstufe 12&lt;/strong&gt;&lt;/p&gt;&#13;&#10;" showErrors="false" sortIndex="0" sourceType="" submitOnChange="false" type="FIXEDRICHTEXT" usageType="" useLabelLeft="false" uuid="0cdbd5a0-7948-4c5e-8ff0-5428b0fd0fb8"/>
      <FormComponent created="15.09.2025 09:31:05" descriptor="TLN_STUNDEN_MODUL_01" importKey="TLN_STUNDEN_MODUL_01" info="" label="Kompetenzfeststellung" mandatory="false" modified="15.09.2025 09:31:05" param1="" param10="" param11="" param12="" param13="" param14="" param15="" param16="" param17="" param18="" param19="" param2="" param20="" param3="" param4="" param5="" param6="" param7="" param8="" param9="" readonly="false" richCLOB="" showErrors="false" sortIndex="1" sourceType="SELF" submitOnChange="false" type="TEXTFIELD" usageType="FLEX_6" useLabelLeft="true" uuid="33d4bb1b-06f2-4237-8689-39b005a3ebc0"/>
      <FormComponent created="15.09.2025 09:31:05" descriptor="TLN_STUNDEN_MODUL_02" importKey="TLN_STUNDEN_MODUL_02" info="" label="Berufsfelderkundung" mandatory="false" modified="15.09.2025 09:31:05" param1="" param10="" param11="" param12="" param13="" param14="" param15="" param16="" param17="" param18="" param19="" param2="" param20="" param3="" param4="" param5="" param6="" param7="" param8="" param9="" readonly="false" richCLOB="" showErrors="false" sortIndex="2" sourceType="SELF" submitOnChange="false" type="TEXTFIELD" usageType="FLEX_6" useLabelLeft="true" uuid="b057f41e-45e7-4f3a-9da8-09f9cd49781c"/>
      <FormComponent created="15.09.2025 09:31:05" descriptor="TLN_STUNDEN_MODUL_03" importKey="TLN_STUNDEN_MODUL_03" info="" label="Vertiefte Praxiserfahrung" mandatory="false" modified="15.09.2025 09:31:05" param1="" param10="" param11="" param12="" param13="" param14="" param15="" param16="" param17="" param18="" param19="" param2="" param20="" param3="" param4="" param5="" param6="" param7="" param8="" param9="" readonly="false" richCLOB="" showErrors="false" sortIndex="3" sourceType="SELF" submitOnChange="false" type="TEXTFIELD" usageType="FLEX_6" useLabelLeft="true" uuid="89cccf25-838f-4842-b05d-5ac15be55633"/>
      <FormComponent created="15.09.2025 09:31:05" descriptor="TLN_STUNDEN_MODUL_04" importKey="TLN_STUNDEN_MODUL_04" info="" label="Übergang" mandatory="false" modified="15.09.2025 09:31:05" param1="" param10="" param11="" param12="" param13="" param14="" param15="" param16="" param17="" param18="" param19="" param2="" param20="" param3="" param4="" param5="" param6="" param7="" param8="" param9="" readonly="false" richCLOB="" showErrors="false" sortIndex="4" sourceType="SELF" submitOnChange="false" type="TEXTFIELD" usageType="FLEX_6" useLabelLeft="true" uuid="50e7c019-d8ed-42de-86e3-08020e6cc22d"/>
    </FormDefinition>
    <FormDefinition collapsed="false" created="16.06.2022 15:00:09" createdBy="Lyonel" forPDF="true" forWeb="true" guid="8b24f0ac-85b7-4cc3-b96b-ea835b20af94" heading="" modified="15.09.2025 09:31:05" modifiedBy="Lyonel" sortIndex="7" uuid="ea686071-9901-4f6a-a7d5-e2c59d103257" visibility="#BILDUNG_JAHRGANGSSTUFE# == '13. Klasse'">
      <FormComponent created="15.09.2025 09:31:05" descriptor="FIXEDTEXT_001" importKey="FIXEDTEXT_001" info="" label="" mandatory="false" modified="15.09.2025 09:31:05" param1="" param10="" param11="" param12="" param13="" param14="" param15="" param16="" param17="" param18="" param19="" param2="" param20="" param3="" param4="" param5="" param6="" param7="" param8="" param9="" readonly="false" richCLOB="&lt;p&gt;&lt;strong&gt;Jahrgangsstufe 13&lt;/strong&gt;&lt;/p&gt;&#13;&#10;" showErrors="false" sortIndex="0" sourceType="" submitOnChange="false" type="FIXEDRICHTEXT" usageType="" useLabelLeft="false" uuid="ec87e678-f611-4655-93e8-72bea355e4a7"/>
      <FormComponent created="15.09.2025 09:31:05" descriptor="TLN_STUNDEN_MODUL_01" importKey="TLN_STUNDEN_MODUL_01" info="" label="Kompetenzfeststellung" mandatory="false" modified="15.09.2025 09:31:05" param1="" param10="" param11="" param12="" param13="" param14="" param15="" param16="" param17="" param18="" param19="" param2="" param20="" param3="" param4="" param5="" param6="" param7="" param8="" param9="" readonly="false" richCLOB="" showErrors="false" sortIndex="1" sourceType="SELF" submitOnChange="false" type="TEXTFIELD" usageType="FLEX_7" useLabelLeft="true" uuid="035834e0-3c46-4815-b8ea-f4548b564f0b"/>
      <FormComponent created="15.09.2025 09:31:05" descriptor="TLN_STUNDEN_MODUL_02" importKey="TLN_STUNDEN_MODUL_02" info="" label="Berufsfelderkundung" mandatory="false" modified="15.09.2025 09:31:05" param1="" param10="" param11="" param12="" param13="" param14="" param15="" param16="" param17="" param18="" param19="" param2="" param20="" param3="" param4="" param5="" param6="" param7="" param8="" param9="" readonly="false" richCLOB="" showErrors="false" sortIndex="2" sourceType="SELF" submitOnChange="false" type="TEXTFIELD" usageType="FLEX_7" useLabelLeft="true" uuid="f75b9a87-24cd-46ae-95ea-1cd75166aed5"/>
      <FormComponent created="15.09.2025 09:31:05" descriptor="TLN_STUNDEN_MODUL_03" importKey="TLN_STUNDEN_MODUL_03" info="" label="Vertiefte Praxiserfahrung" mandatory="false" modified="15.09.2025 09:31:05" param1="" param10="" param11="" param12="" param13="" param14="" param15="" param16="" param17="" param18="" param19="" param2="" param20="" param3="" param4="" param5="" param6="" param7="" param8="" param9="" readonly="false" richCLOB="" showErrors="false" sortIndex="3" sourceType="SELF" submitOnChange="false" type="TEXTFIELD" usageType="FLEX_7" useLabelLeft="true" uuid="7049ebad-b5e7-4460-8d71-662b4d41de9d"/>
      <FormComponent created="15.09.2025 09:31:05" descriptor="TLN_STUNDEN_MODUL_04" importKey="TLN_STUNDEN_MODUL_04" info="" label="Übergang" mandatory="false" modified="15.09.2025 09:31:05" param1="" param10="" param11="" param12="" param13="" param14="" param15="" param16="" param17="" param18="" param19="" param2="" param20="" param3="" param4="" param5="" param6="" param7="" param8="" param9="" readonly="false" richCLOB="" showErrors="false" sortIndex="4" sourceType="SELF" submitOnChange="false" type="TEXTFIELD" usageType="FLEX_7" useLabelLeft="true" uuid="8c320df0-6a1c-4998-adf4-907c06f1ee0d"/>
    </FormDefinition>
    <FormDefinition collapsed="false" created="17.06.2022 11:56:59" createdBy="Lyonel" forPDF="true" forWeb="true" guid="111eb21c-7fcb-457b-9cca-423c769535ec" heading="" modified="15.09.2025 09:31:05" modifiedBy="Lyonel" sortIndex="8" uuid="dbeed94d-197e-49e9-81c2-d196ba53246f" visibility="#GEGENSTAND.LEVEL_CODE# ~ 'BVBO'">
      <FormComponent created="15.09.2025 09:31:05" descriptor="ANTRAG_ANL_ZEIT_ABLAUF" importKey="ANTRAG_ANL_ZEIT_ABLAUF" info="" label=" 5.2 Beschreibung des Angebotsportfolio an der Schule (Benennung der Module in Verbindung mit geplanten Methoden, Jahrgangstufen und Anzahl der SuS) - wie wird die Maßnahme umgesetzt? max. 3000 Zeichen" mandatory="true" modified="15.09.2025 09:31:05" param1="" param10="" param11="" param12="" param13="" param14="" param15="" param16="" param17="" param18="" param19="" param2="" param20="" param3="" param4="" param5="" param6="" param7="" param8="" param9="" readonly="false" richCLOB="" showErrors="false" sortIndex="0" sourceType="SELF" submitOnChange="false" type="RICHTEXT" usageType="" useLabelLeft="false" uuid="dbd2f8a6-67bd-4ba7-834e-a797eed5a508"/>
      <FormComponent created="15.09.2025 09:31:05" descriptor="ANTRAG_ANL_PROJ_BESC" importKey="ANTRAG_ANL_PROJ_BESC" info="" label="5.3 Wie sind die Angebote mit dem Schulkonzept der Berufsorientierung vernetzt und welche Abstimmungen finden hierzu statt? max. 3000 Zeichen" mandatory="true" modified="15.09.2025 09:31:05" param1="" param10="" param11="" param12="" param13="" param14="" param15="" param16="" param17="" param18="" param19="" param2="" param20="" param3="" param4="" param5="" param6="" param7="" param8="" param9="" readonly="false" richCLOB="" showErrors="false" sortIndex="1" sourceType="SELF" submitOnChange="false" type="RICHTEXT" usageType="" useLabelLeft="false" uuid="bb0ffe0c-bcf2-4858-99cd-2156db68ea90"/>
      <FormComponent created="15.09.2025 09:31:05" descriptor="PH_TEXT_LANG_002" importKey="PH_TEXT_LANG_002" info="" label="5.4 Beschreibung der Kooperationen (z.B. mit Wirtschaft, Jobcenter, ggf. weitere Träger, Werk- und Dienstleistungsaufträge - Benennung und Beschreibung der Kooperationen) max. 5000 Zeichen" mandatory="true" modified="15.09.2025 09:31:05" param1="" param10="" param11="" param12="" param13="" param14="" param15="" param16="" param17="" param18="" param19="" param2="" param20="" param3="" param4="" param5="" param6="" param7="" param8="" param9="" readonly="false" richCLOB="" showErrors="false" sortIndex="2" sourceType="SELF" submitOnChange="false" type="RICHTEXT" usageType="" useLabelLeft="false" uuid="c90c4081-58d7-4496-804a-1c29ac2217dd"/>
    </FormDefinition>
    <FormDefinition collapsed="false" created="10.12.2019 15:01:10" createdBy="Lyonel" forPDF="true" forWeb="true" guid="e9a98221-12ab-480f-9f51-f73efaf74716" heading="" modified="15.09.2025 09:31:05" modifiedBy="Lyonel" sortIndex="9" uuid="3c2e1e51-2962-49cb-92f2-303a8f385393" visibility="#GEGENSTAND.LEVEL_CODE# ~ 'BVBO'">
      <FormComponent created="15.09.2025 09:31:05" descriptor="ANTRAG_KURZ_INHALT" importKey="ANTRAG_KURZ_INHALT" info="" label="5.5 Beschreiben Sie kurz das eingesetzte Personal, die Aufgabenstellungen und dessen Qualifikation(en). max. 3000 Zeichen" mandatory="true" modified="15.09.2025 09:31:05" param1="" param10="" param11="" param12="" param13="" param14="" param15="" param16="" param17="" param18="" param19="" param2="" param20="" param3="" param4="" param5="" param6="" param7="" param8="" param9="" readonly="false" richCLOB="" showErrors="true" sortIndex="0" sourceType="SELF" submitOnChange="false" type="RICHTEXT" usageType="" useLabelLeft="false" uuid="ca238d49-3618-45b5-83c0-6a1376109670"/>
    </FormDefinition>
    <FormDefinition collapsed="false" created="31.07.2025 12:43:29" createdBy="Lyonel" forPDF="true" forWeb="true" guid="ad7b3f80-8c24-4681-8176-ef9f3adcae7a" heading="5 Projektbeschreibung" modified="15.09.2025 09:31:05" modifiedBy="Lyonel" sortIndex="10" uuid="f0795453-4c0e-4a0e-95fd-fef1dbf9dd88" visibility="#GEGENSTAND.LEVEL_CODE# == 'KaT'">
      <FormComponent created="15.09.2025 09:31:05" descriptor="FIXEDTEXT_001" importKey="FIXEDTEXT_001" info="" label="" mandatory="false" modified="15.09.2025 09:31:05" param1="" param10="" param11="" param12="" param13="" param14="" param15="" param16="" param17="" param18="" param19="" param2="" param20="" param3="" param4="" param5="" param6="" param7="" param8="" param9="" readonly="false" richCLOB="&lt;p&gt;Bitte laden Sie das Projektkonzept hier hoch. Aus dem Dateinamen sollte hervorgehen, dass es sich um die Projektbeschreibung / das Konzept zum vorliegenden Projekt handelt.&lt;/p&gt;" showErrors="false" sortIndex="0" sourceType="SELF" submitOnChange="false" type="FIXEDRICHTEXT" usageType="" useLabelLeft="false" uuid="28e30411-6a62-4e1d-b63e-96d1a8922bf9"/>
    </FormDefinition>
    <FormDefinition collapsed="false" created="10.12.2019 15:01:10" createdBy="Lyonel" forPDF="true" forWeb="true" guid="0b3ee315-c994-4c2b-b303-dd968167ad28" heading="Nachweisdokument/e Kurzantrag hochladen" modified="15.09.2025 09:31:05" modifiedBy="Lyonel" sortIndex="11" uuid="7ddd5288-9f97-4524-b72e-6dc7e0dc3134" visibility="">
      <FormComponent created="15.09.2025 09:31:05" descriptor="PH_DATEI_005" importKey="PH_DATEI_005" info="" label=" " mandatory="false" modified="15.09.2025 09:31:05" param1="2MB" param10="" param11="" param12="" param13="" param14="" param15="" param16="" param17="" param18="" param19="" param2="" param20="" param3="" param4="" param5="" param6="" param7="" param8="" param9="" readonly="false" richCLOB="" showErrors="true" sortIndex="0" sourceType="SELF" submitOnChange="false" type="UPLOAD_DOWNLOAD" usageType="" useLabelLeft="false" uuid="807fea75-4995-4637-ae58-36b231839094"/>
    </FormDefinition>
  </Webpage>
  <Webpage avoidPagebreak="false" created="10.12.2019 15:01:10" createdBy="Lyonel" guid="226df90a-1427-41cc-b1f9-72ae8e7093c7" heading="Erklärung des ZE" hideIfEmpty="false" modified="15.09.2025 09:31:05" modifiedBy="Lyonel" print="" sortIndex="5" uuid="e6034ced-23c7-4cfc-a102-aef93e894752">
    <FormDefinition collapsed="false" created="10.12.2019 15:01:10" createdBy="Lyonel" forPDF="false" forWeb="true" guid="8717040f-78e8-4517-8c05-3fd42cc4e5f0" heading="Erklärung des Zuwendungsempfängers" modified="15.09.2025 09:31:05" modifiedBy="Lyonel" sortIndex="0" uuid="25172778-45b1-42e9-95ec-ff00184051b7" visibility="">
      <FormComponent created="15.09.2025 09:31:05" descriptor="FIXEDTEXT_001" importKey="FIXEDTEXT_001" info="" label="" mandatory="false" modified="15.09.2025 09:31:05" param1="" param10="" param11="" param12="" param13="" param14="" param15="" param16="" param17="" param18="" param19="" param2="" param20="" param3="" param4="" param5="" param6="" param7="" param8="" param9="" readonly="false" richCLOB="&lt;p&gt;&lt;span style=&quot;font-size:small&quot;&gt;&amp;nbsp;&lt;span style=&quot;font-size:12px&quot;&gt;&lt;strong&gt;Der/Die Unterzeichnende erklärt,&lt;/strong&gt;&lt;/span&gt;&lt;/span&gt;&lt;/p&gt;&#13;&#10;&#13;&#10;&lt;ul&gt;&#13;&#10;&#9;&lt;li&gt;&lt;span style=&quot;font-size:12px&quot;&gt;dass mit der beantragten Maßnahme noch nicht begonnen wurde,&lt;/span&gt;&lt;/li&gt;&#13;&#10;&#9;&lt;li&gt;&lt;span style=&quot;font-size:12px&quot;&gt;sich mit der Weitergabe der erhobenen Daten an Dienststellen der Länder und des Bundes sowie ihrer Verwendung zu Zwecken öffentlicher Informationen einverstanden,&lt;/span&gt;&lt;/li&gt;&#13;&#10;&#9;&lt;li&gt;&lt;span style=&quot;font-size:12px&quot;&gt;die Einwilligung dazu, dass die Angaben gemäß Nr. 1.5 AV zu § 44 LHO (Name und Postanschrift des Zuwendungsempfängers, Art ,Höhe und Zweck der Zuwendung) im Zusammenhang mit der von uns beantragten Zuwendung im Falle einer Bewilligung in der Zuwendungsdatenbank des Landes Berlin veröffentlicht werden,&lt;/span&gt;&lt;/li&gt;&#13;&#10;&#9;&lt;li&gt;&lt;span style=&quot;font-size:12px&quot;&gt;dass zum gleichen Zweck bei anderen Dienststellen des Landes Berlin, den Agenturen für Arbeit und Jobcentern kein Antrag auf Gewährung von Zuschüssen/Zuwendungen gestellt worden ist,&amp;nbsp;&lt;/span&gt;&lt;/li&gt;&#13;&#10;&#9;&lt;li&gt;&lt;span style=&quot;font-size:12px&quot;&gt;dass mir bekannt ist, dass die Zuweisung aus Mitteln des Landes Berlin eine Subvention darstellt und die vorstehenden Angaben subventionserhebliche Tatsache im Sinne von § 264 des Strafgesetzbuches (StGB) in Verbindung mit § 2 des Subventionsgesetzes vom 29. Juli 1976 (BGBl. I S. 2034/GVBl. S. 1711) und § 1 des Landessubventionsgesetzes vom 20. Juni 1977 (GVBl. &amp;nbsp;S. 1126) sind und nach § 3 des Subventionsgesetzes den Subventionsnehmer eine sich auf alle subventionserheblichen Tatsachen erstreckende Offenbarungspflicht trifft,&lt;/span&gt;&lt;/li&gt;&#13;&#10;&#9;&lt;li&gt;&lt;span style=&quot;font-size:12px&quot;&gt;dass mir bekannt ist, dass subventionserhebliche Tatsachen auch solche sind, die durch Scheingeschäfte oder Scheinhandlungen verdeckt werden sowie Rechtsgeschäfte oder Handlungen unter Missbrauch von Gestaltungsmöglichkeiten im Zusammenhang mit einer beantragten Zuwendung (§ 4 des Subventionsgesetzes) und die Verpflichtung besteht, der bewilligenden Stelle unverzüglich und unaufgefordert alle Änderungen der subventionserheblichen Tatsachen mitzuteilen,&lt;/span&gt;&lt;/li&gt;&#13;&#10;&#9;&lt;li&gt;&lt;span style=&quot;font-size:12px&quot;&gt;die sachgerechte Durchführung des Projektes und interne Kontrolle und&lt;/span&gt;&lt;/li&gt;&#13;&#10;&#9;&lt;li&gt;&lt;span style=&quot;font-size:12px&quot;&gt;dass die beantragten Mittel im Falle der Bewilligung wirtschaftlich und sparsam verwendet werden.&lt;/span&gt;&lt;br&gt;&#13;&#10;&#9;&amp;nbsp;&lt;/li&gt;&#13;&#10;&lt;/ul&gt;&#13;&#10;" showErrors="false" sortIndex="0" sourceType="SELF" submitOnChange="false" type="FIXEDRICHTEXT" usageType="" useLabelLeft="false" uuid="e41b25f6-0634-42e0-a6c7-851da81e338e"/>
    </FormDefinition>
    <FormDefinition collapsed="false" created="10.12.2019 15:01:10" createdBy="Lyonel" forPDF="true" forWeb="false" guid="2d798e05-444a-45dd-b270-3ad4730c0253" heading="Erklärung des Zuwendungsempfängers" modified="15.09.2025 09:31:05" modifiedBy="Lyonel" sortIndex="1" uuid="ed2347e8-6abf-45b5-920c-648015a64e0c" visibility="">
      <FormComponent created="15.09.2025 09:31:05" descriptor="FIXEDTEXT_001" importKey="FIXEDTEXT_001" info="" label="" mandatory="false" modified="15.09.2025 09:31:05" param1="" param10="" param11="" param12="" param13="" param14="" param15="" param16="" param17="" param18="" param19="" param2="" param20="" param3="" param4="" param5="" param6="" param7="" param8="" param9="" readonly="false" richCLOB="&lt;p&gt;&lt;span style=&quot;font-size:small&quot;&gt;&amp;nbsp;&lt;span style=&quot;font-size:10.5px&quot;&gt;&lt;strong&gt;Der/Die Unterzeichnende erklärt,&lt;/strong&gt;&lt;/span&gt;&lt;/span&gt;&lt;/p&gt;&#13;&#10;&#13;&#10;&lt;ul&gt;&#13;&#10;&#9;&lt;li&gt;&lt;span style=&quot;font-size:10.5px&quot;&gt;dass mit der beantragten Maßnahme noch nicht begonnen wurde,&lt;/span&gt;&lt;/li&gt;&#13;&#10;&#9;&lt;li&gt;&lt;span style=&quot;font-size:10.5px&quot;&gt;sich mit der Weitergabe der erhobenen Daten an Dienststellen der Länder und des Bundes sowie ihrer Verwendung zu Zwecken öffentlicher Informationen einverstanden,&lt;/span&gt;&lt;/li&gt;&#13;&#10;&#9;&lt;li&gt;&lt;span style=&quot;font-size:10.5px&quot;&gt;die Einwilligung dazu, dass die Angaben gemäß Nr. 1.5 AV zu § 44 LHO (Name und Postanschrift des Zuwendungsempfängers, Art ,Höhe und Zweck der Zuwendung) im Zusammenhang mit der von uns beantragten Zuwendung im Falle einer Bewilligung in der Zuwendungsdatenbank des Landes Berlin veröffentlicht werden,&lt;/span&gt;&lt;/li&gt;&#13;&#10;&#9;&lt;li&gt;&lt;span style=&quot;font-size:10.5px&quot;&gt;dass zum gleichen Zweck bei anderen Dienststellen des Landes Berlin, den Agenturen für Arbeit und Jobcentern kein Antrag auf Gewährung von Zuschüssen/Zuwendungen gestellt worden ist,&amp;nbsp;&lt;/span&gt;&lt;/li&gt;&#13;&#10;&#9;&lt;li&gt;&lt;span style=&quot;font-size:10.5px&quot;&gt;dass mir bekannt ist, dass die Zuweisung aus Mitteln des Landes Berlin eine Subvention darstellt und die vorstehenden Angaben subventionserhebliche Tatsache im Sinne von § 264 des Strafgesetzbuches (StGB) in Verbindung mit § 2 des Subventionsgesetzes vom 29. Juli 1976 (BGBl. I S. 2034/GVBl. S. 1711) und § 1 des Landessubventionsgesetzes vom 20. Juni 1977 (GVBl. &amp;nbsp;S. 1126) sind und nach § 3 des Subventionsgesetzes den Subventionsnehmer eine sich auf alle subventionserheblichen Tatsachen erstreckende Offenbarungspflicht trifft,&lt;/span&gt;&lt;/li&gt;&#13;&#10;&#9;&lt;li&gt;&lt;span style=&quot;font-size:10.5px&quot;&gt;dass mir bekannt ist, dass subventionserhebliche Tatsachen auch solche sind, die durch Scheingeschäfte oder Scheinhandlungen verdeckt werden sowie Rechtsgeschäfte oder Handlungen unter Missbrauch von Gestaltungsmöglichkeiten im Zusammenhang mit einer beantragten Zuwendung (§ 4 des Subventionsgesetzes) und die Verpflichtung besteht, der bewilligenden Stelle unverzüglich und unaufgefordert alle Änderungen der subventionserheblichen Tatsachen mitzuteilen,&lt;/span&gt;&lt;/li&gt;&#13;&#10;&#9;&lt;li&gt;&lt;span style=&quot;font-size:10.5px&quot;&gt;die sachgerechte Durchführung des Projektes und interne Kontrolle und&lt;/span&gt;&lt;/li&gt;&#13;&#10;&#9;&lt;li&gt;&lt;span style=&quot;font-size:10.5px&quot;&gt;dass die beantragten Mittel im Falle der Bewilligung wirtschaftlich und sparsam verwendet werden.&lt;/span&gt;&lt;br&gt;&#13;&#10;&#9;&amp;nbsp;&lt;/li&gt;&#13;&#10;&lt;/ul&gt;&#13;&#10;" showErrors="false" sortIndex="0" sourceType="SELF" submitOnChange="false" type="FIXEDRICHTEXT" usageType="" useLabelLeft="false" uuid="3c66de18-4719-4ade-8a0d-84d2a9dc29a0"/>
    </FormDefinition>
    <FormDefinition collapsed="false" created="10.12.2019 15:01:10" createdBy="Lyonel" forPDF="true" forWeb="true" guid="763e98c8-9e8f-4e1a-b489-214807e2d43d" heading="Des Weiteren erklärt der Zuwendungsempfänger, dass bezüglich" modified="15.09.2025 09:31:05" modifiedBy="Lyonel" sortIndex="2" uuid="5d2ff14e-fa8f-4cdb-8696-346c806fd89f" visibility="">
      <FormComponent created="15.09.2025 09:31:05" descriptor="ANTRAG_ERKL_B_VST_ABZ" importKey="ANTRAG_ERKL_B_VST_ABZ" info="" label="des Vorsteuerabzugs, " mandatory="true" modified="15.09.2025 09:31:05" param1="" param10="" param11="" param12="" param13="" param14="" param15="" param16="" param17="" param18="" param19="" param2="" param20="" param3="" param4="" param5="" param6="" param7="" param8="" param9="" readonly="false" richCLOB="" showErrors="true" sortIndex="0" sourceType="SELF" submitOnChange="false" type="SELECT_ONE_RADIO_VERTICAL" usageType="" useLabelLeft="false" uuid="ef253ed0-bb63-4a87-816e-935288192e7d"/>
    </FormDefinition>
    <FormDefinition collapsed="false" created="10.12.2019 15:01:10" createdBy="Lyonel" forPDF="true" forWeb="true" guid="994219e8-2e03-436d-84dc-fc04c6697cf8" heading="" modified="15.09.2025 09:31:05" modifiedBy="Lyonel" sortIndex="3" uuid="e753dadb-ae75-4261-9584-a50d40e5cda7" visibility="">
      <FormComponent created="15.09.2025 09:31:05" descriptor="FIXEDTEXT_013" importKey="FIXEDTEXT_013" info="" label="" mandatory="false" modified="15.09.2025 09:31:05" param1="" param10="" param11="" param12="" param13="" param14="" param15="" param16="" param17="" param18="" param19="" param2="" param20="" param3="" param4="" param5="" param6="" param7="" param8="" param9="" readonly="false" richCLOB="&lt;p&gt;&lt;strong&gt;Des Weiteren erklärt der Zuwendungsempfänger, dass die nachfolgend rechtsgültig aufgeführten Dokumente in die Trägerakte hochgeladen wurden:&lt;/strong&gt;&lt;/p&gt;" showErrors="true" sortIndex="0" sourceType="" submitOnChange="false" type="FIXEDRICHTEXT" usageType="" useLabelLeft="false" uuid="cd880ff0-3209-4e15-9cb9-bb136cedc312"/>
      <FormComponent created="15.09.2025 09:31:05" descriptor="PH_CHECKBOX_098" importKey="PH_CHECKBOX_098" info="" label="" mandatory="true" modified="15.09.2025 09:31:05" param1="" param10="" param11="" param12="" param13="" param14="" param15="" param16="" param17="" param18="" param19="" param2="" param20="" param3="" param4="" param5="" param6="" param7="" param8="" param9="" readonly="false" richCLOB="" showErrors="true" sortIndex="1" sourceType="SELF" submitOnChange="false" type="SELECT_ONE_CHECKBOX" usageType="" useLabelLeft="false" uuid="445c0af1-85c1-4450-89ed-2975ccb1b4a8"/>
      <FormComponent created="15.09.2025 09:31:05" descriptor="PH_CHECKBOX_099" importKey="PH_CHECKBOX_099" info="" label="" mandatory="true" modified="15.09.2025 09:31:05" param1="" param10="" param11="" param12="" param13="" param14="" param15="" param16="" param17="" param18="" param19="" param2="" param20="" param3="" param4="" param5="" param6="" param7="" param8="" param9="" readonly="false" richCLOB="" showErrors="true" sortIndex="2" sourceType="SELF" submitOnChange="false" type="SELECT_ONE_CHECKBOX" usageType="" useLabelLeft="false" uuid="dd443c31-9e0a-475b-8f57-d32adfe70006"/>
    </FormDefinition>
  </Webpage>
  <Webpage avoidPagebreak="false" created="10.12.2019 15:01:10" createdBy="Lyonel" guid="1e06412a-a315-46b2-8700-425fef595570" heading="Erklärung zur LGV" hideIfEmpty="false" modified="15.09.2025 09:31:05" modifiedBy="Lyonel" print="" sortIndex="6" uuid="914c5698-2d76-421c-92c3-c49b04acb5a1">
    <FormDefinition collapsed="false" created="10.12.2019 15:01:10" createdBy="Lyonel" forPDF="true" forWeb="true" guid="370fdcdb-9215-4db3-80e5-3e21817ce951" heading="Erklärung zur Leistungsgewährungsverordnung" modified="15.09.2025 09:31:05" modifiedBy="Lyonel" sortIndex="0" uuid="61870c54-af30-490c-838a-11288a790adb" visibility="">
      <FormComponent created="15.09.2025 09:31:05" descriptor="PH_NKL_009" importKey="PH_NKL_009" info="" label="Der/Die Unterzeichnende erklärt:" mandatory="true" modified="15.09.2025 09:31:05" param1="" param10="" param11="" param12="" param13="" param14="" param15="" param16="" param17="" param18="" param19="" param2="" param20="" param3="" param4="" param5="" param6="" param7="" param8="" param9="" readonly="false" richCLOB="" showErrors="false" sortIndex="0" sourceType="SELF" submitOnChange="true" type="SELECT_ONE_RADIO_VERTICAL" usageType="" useLabelLeft="false" uuid="45c3160c-ec4b-41ec-9282-8bf2a6e02640"/>
      <FormComponent created="15.09.2025 09:31:05" descriptor="PH_CHECKBOX_007" importKey="PH_CHECKBOX_007" info="" label="" mandatory="false" modified="15.09.2025 09:31:05" param1="" param10="" param11="" param12="" param13="" param14="" param15="" param16="" param17="" param18="" param19="" param2="" param20="" param3="" param4="" param5="" param6="" param7="" param8="" param9="" readonly="false" richCLOB="" showErrors="false" sortIndex="1" sourceType="SELF" submitOnChange="false" type="SELECT_ONE_CHECKBOX" usageType="" useLabelLeft="false" uuid="917ca69f-7042-4902-b9ae-1b0e1c449578"/>
    </FormDefinition>
    <FormDefinition collapsed="false" created="10.12.2019 15:01:10" createdBy="Lyonel" forPDF="true" forWeb="true" guid="059bb99a-26b1-4ce5-b837-5b9cd347bbd3" heading="Anlagen zur LGV" modified="15.09.2025 09:31:05" modifiedBy="Lyonel" sortIndex="1" uuid="5f86dd37-9fa3-4a62-a589-f5f6576e9b6d" visibility="PH_NKL_009 == '02'">
      <FormComponent created="15.09.2025 09:31:05" descriptor="FIXEDTEXT_006" importKey="FIXEDTEXT_006" info="" label="" mandatory="false" modified="15.09.2025 09:31:05" param1="" param10="" param11="" param12="" param13="" param14="" param15="" param16="" param17="" param18="" param19="" param2="" param20="" param3="" param4="" param5="" param6="" param7="" param8="" param9="" readonly="false" richCLOB="&lt;p&gt;Erklärung gemäß § 3 Absatz 1 der Leistungsgewährungsverordnung (LGV)&lt;br&gt;(entspricht der Anlage zu § 3 Abs. 1 LGV)&lt;br&gt;&lt;br&gt;Hiermit erkläre(n) ich/wir Folgendes:&lt;/p&gt;&#13;&#10;&lt;p&gt;&lt;strong&gt;&lt;br&gt;Anwendbarkeit von § 14 Absatz 1 des Landesgleichstellungsgesetzes&lt;/strong&gt;&lt;/p&gt;" showErrors="true" sortIndex="0" sourceType="" submitOnChange="false" type="FIXEDRICHTEXT" usageType="" useLabelLeft="false" uuid="16431371-d54c-4ed3-b37b-a3151cbc0fd7"/>
      <FormComponent created="15.09.2025 09:31:05" descriptor="PH_CHECKBOX_006" importKey="PH_CHECKBOX_006" info="" label="Bei dem/der Leistungsempfangenden sind in der Regel mehr als zehn Arbeitnehmerinnen/ Arbeitnehmer beschäftigt (ausschließlich der zu ihrer Berufsbildung Beschäftigten)" mandatory="false" modified="15.09.2025 09:31:05" param1="" param10="" param11="" param12="" param13="" param14="" param15="" param16="" param17="" param18="" param19="" param2="" param20="" param3="" param4="" param5="" param6="" param7="" param8="" param9="" readonly="false" richCLOB="" showErrors="false" sortIndex="1" sourceType="SELF" submitOnChange="true" type="SELECT_ONE_CHECKBOX" usageType="" useLabelLeft="false" uuid="7067da55-8bcd-40c6-a372-36f241ee134d"/>
    </FormDefinition>
    <FormDefinition collapsed="false" created="10.12.2019 15:01:10" createdBy="Lyonel" forPDF="true" forWeb="true" guid="8eda1442-9301-46ff-b4f9-5a257fa9f64a" heading="I. Beschäftigtenzahl" modified="15.09.2025 09:31:05" modifiedBy="Lyonel" sortIndex="2" uuid="bf5ada40-deed-4a93-93e2-afeedf016172" visibility="PH_CHECKBOX_006==true">
      <FormComponent created="15.09.2025 09:31:05" descriptor="ANTRAG_KMU" importKey="ANTRAG_KMU" info="über 500 Beschäftigte&#13;&#10;&#13;&#10;(→ gemäß §4 Absatz 2 Nummer 1 der Leistungsgewährungsverordnung sind drei der in § 4 Absatz 1 der Leistungsgewährungsverordnung genannten Maßnahmen zur Förderung von Frauen und/oder der Vereinbarkeit von Beruf und Familie auszuwählen, davon mindestens eine Maßnahme der Nummern 1 bis 6)&#13;&#10;&#13;&#10;über 250 bis 500 Beschäftigte&#13;&#10;&#13;&#10;(→ gemäß § 4 Absatz 2 Nummer 2 der Leistungsgewährungsverordnung sind drei der in § 4 Absatz 1 der Leistungsgewährungsverordnung genannten Maßnahmen zur Förderung von Frauen und/oder der Vereinbarkeit von Beruf und Familie auszuwählen)&#13;&#10;&#13;&#10;über 20 bis 250 Beschäftigte&#13;&#10;&#13;&#10;(→ gemäß § 4 Absatz 2 Nummer 3 der Leistungsgewährungsverordnung sind zwei der in § 4 Absatz 1 der Leistungsgewährungsverordnung genannten Maßnahmen zur Förderung von Frauen und/oder der Vereinbarkeit von Beruf und Familie auszuwählen)&#13;&#10;&#13;&#10;über 10 bis 20 Beschäftigte&#13;&#10;&#13;&#10;(→ gemäß § 4 Absatz 2 Nummer 4 der Leistungsgewährungsverordnung ist eine der in § 4 Absatz 1 Nummer 1 bis 20 der Leistungsgewährungsverordnung genannten Maßnahmen zur Förderung von Frauen und/oder der Vereinbarkeit von Beruf und Familie auszuwählen)" label="Bei dem/der Leistungsempfangenden sind in der Regel beschäftigt: " mandatory="true" modified="15.09.2025 09:31:05" param1="" param10="" param11="" param12="" param13="" param14="" param15="" param16="" param17="" param18="" param19="" param2="" param20="" param3="" param4="" param5="" param6="" param7="" param8="" param9="" readonly="false" richCLOB="" showErrors="true" sortIndex="0" sourceType="SELF" submitOnChange="false" type="SELECT_ONE_RADIO_VERTICAL" usageType="" useLabelLeft="false" uuid="c8f2f66e-0ba8-4a1c-a977-050c7e0e395c"/>
    </FormDefinition>
    <FormDefinition collapsed="false" created="10.12.2019 15:01:10" createdBy="Lyonel" forPDF="true" forWeb="true" guid="0ab2c8ee-ecd0-4577-a674-1738dec4d8f9" heading="II. Maßnahmen zur Frauenförderung und/oder zur Förderung der Vereinbarkeit von Beruf und Familie" modified="15.09.2025 09:31:05" modifiedBy="Lyonel" sortIndex="3" uuid="847b76f8-e97c-493a-9592-b1fae06b8323" visibility="PH_CHECKBOX_006==true">
      <FormComponent created="15.09.2025 09:31:05" descriptor="FIXEDTEXT_008" importKey="FIXEDTEXT_008" info="" label="" mandatory="false" modified="15.09.2025 09:31:05" param1="" param10="" param11="" param12="" param13="" param14="" param15="" param16="" param17="" param18="" param19="" param2="" param20="" param3="" param4="" param5="" param6="" param7="" param8="" param9="" readonly="false" richCLOB="&lt;p&gt;Ich/Wir verpflichte(n) mich/uns zur Durchführung oder Einleitung folgender Maßnahme(n) gemäß § 4 Absatz 1 der Leistungsgewährungsverordnung:&lt;/p&gt;" showErrors="true" sortIndex="0" sourceType="" submitOnChange="false" type="FIXEDRICHTEXT" usageType="" useLabelLeft="false" uuid="ab3f3e44-86b5-4f2b-a607-840b8ca772aa"/>
      <FormComponent created="15.09.2025 09:31:05" descriptor="ANTRAG_FRAUENFOERDERUNG" importKey="ANTRAG_FRAUENFOERDERUNG" info="" label=" " mandatory="true" modified="15.09.2025 09:31:05" param1="" param10="" param11="" param12="" param13="" param14="" param15="" param16="" param17="" param18="" param19="" param2="" param20="" param3="" param4="" param5="" param6="" param7="" param8="" param9="" readonly="false" richCLOB="" showErrors="true" sortIndex="1" sourceType="SELF" submitOnChange="false" type="SELECT_MANY_CHECKBOX" usageType="" useLabelLeft="false" uuid="41465e76-c3da-481b-897e-362e045e92c7"/>
    </FormDefinition>
    <FormDefinition collapsed="false" created="10.12.2019 15:01:10" createdBy="Lyonel" forPDF="true" forWeb="true" guid="f023143c-f174-4b3a-960e-a42603b58798" heading="III. (Erforderlichenfalls anzugeben) Antrag zur Befreiung von der Verpflichtung zur Durchführung von Maßnahmen zur Frauenförderung und/oder zur Förderung der Vereinbarkeit von Beruf und Familie" modified="15.09.2025 09:31:05" modifiedBy="Lyonel" sortIndex="4" uuid="9356997e-ddfe-4088-a2f2-65342033989b" visibility="PH_CHECKBOX_006==true AND ANTRAG_FRAUENFOERDERUNG ~ 22">
      <FormComponent created="15.09.2025 09:31:05" descriptor="FIXEDTEXT_009" importKey="FIXEDTEXT_009" info="" label="" mandatory="false" modified="15.09.2025 09:31:05" param1="" param10="" param11="" param12="" param13="" param14="" param15="" param16="" param17="" param18="" param19="" param2="" param20="" param3="" param4="" param5="" param6="" param7="" param8="" param9="" readonly="false" richCLOB="&lt;p&gt;Von der Verpflichtung zur Durchführung von den unter II. aufgeführten Maßnahmen beantrage ich die Befreiung, da die Beschäftigung von Männern aus rechtlichen oder tatsächlichen Gründen aus nachfolgenden Gründen unabdingbar ist.&lt;/p&gt;" showErrors="true" sortIndex="0" sourceType="" submitOnChange="false" type="FIXEDRICHTEXT" usageType="" useLabelLeft="false" uuid="154d51aa-ffc9-47d9-843e-e0c473e8382b"/>
      <FormComponent created="15.09.2025 09:31:06" descriptor="PH_TEXT_LANG_003" importKey="PH_TEXT_LANG_003" info="" label="Begründung:" mandatory="true" modified="15.09.2025 09:31:06" param1="" param10="" param11="" param12="" param13="" param14="" param15="" param16="" param17="" param18="" param19="" param2="" param20="" param3="" param4="" param5="" param6="" param7="" param8="" param9="" readonly="false" richCLOB="" showErrors="false" sortIndex="1" sourceType="SELF" submitOnChange="false" type="TEXTAREA" usageType="" useLabelLeft="false" uuid="60e08841-ae9c-41e5-be2f-77768c7445cf"/>
      <FormComponent created="15.09.2025 09:31:06" descriptor="FIXEDTEXT_011" importKey="FIXEDTEXT_011" info="" label="" mandatory="false" modified="15.09.2025 09:31:06" param1="" param10="" param11="" param12="" param13="" param14="" param15="" param16="" param17="" param18="" param19="" param2="" param20="" param3="" param4="" param5="" param6="" param7="" param8="" param9="" readonly="false" richCLOB="&lt;p&gt;Mir/Uns ist bekannt, dass Falschangaben im Rahmen dieser Erklärung oder die Nichterfüllung der Auflage gemäß § 3 Absatz 1 der Leistungsgewährungsverordnung zum Widerruf oder zur Rücknahme der gewährten Leistung führen können.&lt;/p&gt;" showErrors="true" sortIndex="2" sourceType="" submitOnChange="false" type="FIXEDRICHTEXT" usageType="" useLabelLeft="false" uuid="d515e807-5fe2-49b0-86ee-1b216307342a"/>
    </FormDefinition>
    <FormDefinition collapsed="false" created="10.12.2019 15:01:10" createdBy="Lyonel" forPDF="true" forWeb="false" guid="ca413527-cf30-4e20-a784-e7fd44232f14" heading="" modified="15.09.2025 09:31:06" modifiedBy="Lyonel" sortIndex="5" uuid="7f9aa5bf-2e09-4a15-a878-c443e1db0538" visibility="">
      <FormComponent created="15.09.2025 09:31:06" descriptor="FIXEDTEXT_011" importKey="FIXEDTEXT_011" info="" label="" mandatory="false" modified="15.09.2025 09:31:06" param1="" param10="" param11="" param12="" param13="" param14="" param15="" param16="" param17="" param18="" param19="" param2="" param20="" param3="" param4="" param5="" param6="" param7="" param8="" param9="" readonly="false" richCLOB="&lt;table border=&quot;0&quot; cellpadding=&quot;3&quot; style=&quot;width:100%&quot;&gt;&#13;&#10;&#9;&lt;tbody&gt;&#13;&#10;&#9;&#9;&lt;tr&gt;&#13;&#10;&#9;&#9;&#9;&lt;td&gt;&amp;nbsp;&lt;/td&gt;&#13;&#10;&#9;&#9;&lt;/tr&gt;&#13;&#10;&#9;&#9;&lt;tr&gt;&#13;&#10;&#9;&#9;&#9;&lt;td&gt;&amp;nbsp;&lt;/td&gt;&#13;&#10;&#9;&#9;&lt;/tr&gt;&#13;&#10;&#9;&#9;&lt;tr&gt;&#13;&#10;&#9;&#9;&#9;&lt;td&gt;&amp;nbsp;&lt;/td&gt;&#13;&#10;&#9;&#9;&lt;/tr&gt;&#13;&#10;&#9;&#9;&lt;tr&gt;&#13;&#10;&#9;&#9;&#9;&lt;td&gt;&lt;u style=&quot;text-decoration:underline&quot;&gt;&lt;strong&gt;&lt;span style=&quot;font-size:small&quot;&gt;&amp;nbsp;&amp;nbsp;&amp;nbsp;&amp;nbsp;&amp;nbsp;&amp;nbsp;&amp;nbsp;&amp;nbsp;&amp;nbsp;&amp;nbsp;&amp;nbsp;&amp;nbsp;&amp;nbsp;&amp;nbsp;&amp;nbsp;&amp;nbsp;&amp;nbsp;&amp;nbsp;&amp;nbsp;&amp;nbsp;&amp;nbsp;&amp;nbsp;&amp;nbsp;&amp;nbsp;&amp;nbsp;&amp;nbsp;&amp;nbsp;&amp;nbsp;&amp;nbsp;&amp;nbsp;&amp;nbsp;&amp;nbsp;&amp;nbsp;&amp;nbsp;&amp;nbsp;&amp;nbsp;&amp;nbsp;&amp;nbsp;&amp;nbsp;&amp;nbsp;&amp;nbsp;&amp;nbsp;&amp;nbsp;&amp;nbsp;&amp;nbsp;&amp;nbsp;&amp;nbsp;&amp;nbsp;&amp;nbsp;&amp;nbsp;&amp;nbsp;&amp;nbsp;&amp;nbsp;&amp;nbsp;&amp;nbsp;&amp;nbsp;&amp;nbsp;&amp;nbsp;&amp;nbsp;&amp;nbsp;&amp;nbsp;&amp;nbsp;&amp;nbsp;&amp;nbsp;&amp;nbsp;&amp;nbsp;&amp;nbsp;&amp;nbsp;&amp;nbsp;&amp;nbsp;&amp;nbsp;&amp;nbsp;&amp;nbsp;&amp;nbsp;&amp;nbsp;&amp;nbsp;&amp;nbsp;&amp;nbsp;&amp;nbsp;&amp;nbsp;&lt;/span&gt;&lt;/strong&gt;&lt;/u&gt;&lt;/td&gt;&#13;&#10;&#9;&#9;&lt;/tr&gt;&#13;&#10;&#9;&#9;&lt;tr&gt;&#13;&#10;&#9;&#9;&#9;&lt;td style=&quot;text-align: justify;&quot;&gt;&lt;span style=&quot;font-size:10.5px&quot;&gt;Datum, Unterschrift des Zuwendungsempfängers&lt;/span&gt;&lt;/td&gt;&#13;&#10;&#9;&#9;&lt;/tr&gt;&#13;&#10;&#9;&lt;/tbody&gt;&#13;&#10;&lt;/table&gt;&#13;&#10;" showErrors="true" sortIndex="0" sourceType="" submitOnChange="false" type="FIXEDRICHTEXT" usageType="" useLabelLeft="false" uuid="ab46bd14-4790-4f5d-9e72-ff0380f5b1bc"/>
    </FormDefinition>
  </Webpage>
</PageFlow>
